Workbook

Sheet 使い方
A1: note 販売 KPI 記録表
A3: 黄色のセル（青い文字）だけ入力します。ほかは自動で計算されます。
A4: 1. 商品シート：note に公開したら、公開日と価格を入れる（値上げしたら価格を書き換える）
A5: 2. 週次シート：毎週、商品ごとに1行。note のダッシュボードの「記事ごとのビュー」と、売上履歴の購入数を入れる
A6: 3. 月次シート：月末に、フォロワー数・全体ビュー・メンバー数を入れる。単品の売上は週次から自動で集計される
A8: 見方
A9: ・購入率＝購入数 ÷ 有料記事のビュー。1%未満なら無料部分（何が手に入るか）を直す。2%以上なら値上げを検討する
A10: ・高評価率＝高評価 ÷ 購入数。40%未満なら、無料部分の説明と中身のズレを疑う
A11: ・手取りは設定シートの手取り率（初期値：カード決済の85.5%）で見積もる。実際の入金額は note の売上管理で確認する

Sheet 設定
A1: 設定
B4: 手取り率 | C4: 0.855 | D4: クレジットカード決済：事務手数料5%＋残額にプラットフォーム利用料10%。キャリア決済が多いと下がる
B5: 目標（手取り・月） | C5: 1000000 | D5: note/README.md の3章

Sheet 商品
A1: 商品一覧
A3: ID | B3: 商品名 | C3: 価格（円） | D3: 公開日 | E3: note の URL
A4: P1 | B4: 買取せどりの仕入れ判定・入金管理シート | C4: 980
A5: P2 | B5: Amazon物販 利益・現金・在庫の監査キット | C5: 2980
A6: P3 | B6: 中国OEM 見積比較・検品・補償交渉キット | C6: 4980
A7: P4 | B7: 新商品の GO／NO-GO 判定シート | C7: 2980
A8: P5 | B8: 物販の利益管理 完全パック | C8: 14800

Sheet 週次
A1: 週次の記録（商品ごとに1行）
A2: 記入例の1行は消してかまいません。
A4: 週の開始日 | B4: 商品ID | C4: 有料記事 ビュー | D4: 購入数 | E4: 高評価 | F4: 返金 | G4: 価格 | H4: 売上 | I4: 手取り見込み | J4: 購入率 | K4: 高評価率
A5: 46293 | B5: P1 | C5: 300 | D5: 3 | E5: 1 | F5: 0 | G5: =IF($B5="","",IFERROR(INDEX('商品'!$C$4:$C$18,MATCH($B5,'商品'!$A$4:$A$18,0)),"")) | H5: =IF(OR($B5="",$G5=""),"",$G5*(N($D5)-N($F5))) | I5: =IF($H5="","",$H5*'設定'!$C$4) | J5: =IF(N($C5)=0,"",N($D5)/$C5) | K5: =IF(N($D5)=0,"",N($E5)/$D5)
G6: =IF($B6="","",IFERROR(INDEX('商品'!$C$4:$C$18,MATCH($B6,'商品'!$A$4:$A$18,0)),"")) | H6: =IF(OR($B6="",$G6=""),"",$G6*(N($D6)-N($F6))) | I6: =IF($H6="","",$H6*'設定'!$C$4) | J6: =IF(N($C6)=0,"",N($D6)/$C6) | K6: =IF(N($D6)=0,"",N($E6)/$D6)
G7: =IF($B7="","",IFERROR(INDEX('商品'!$C$4:$C$18,MATCH($B7,'商品'!$A$4:$A$18,0)),"")) | H7: =IF(OR($B7="",$G7=""),"",$G7*(N($D7)-N($F7))) | I7: =IF($H7="","",$H7*'設定'!$C$4) | J7: =IF(N($C7)=0,"",N($D7)/$C7) | K7: =IF(N($D7)=0,"",N($E7)/$D7)
G8: =IF($B8="","",IFERROR(INDEX('商品'!$C$4:$C$18,MATCH($B8,'商品'!$A$4:$A$18,0)),"")) | H8: =IF(OR($B8="",$G8=""),"",$G8*(N($D8)-N($F8))) | I8: =IF($H8="","",$H8*'設定'!$C$4) | J8: =IF(N($C8)=0,"",N($D8)/$C8) | K8: =IF(N($D8)=0,"",N($E8)/$D8)
G9: =IF($B9="","",IFERROR(INDEX('商品'!$C$4:$C$18,MATCH($B9,'商品'!$A$4:$A$18,0)),"")) | H9: =IF(OR($B9="",$G9=""),"",$G9*(N($D9)-N($F9))) | I9: =IF($H9="","",$H9*'設定'!$C$4) | J9: =IF(N($C9)=0,"",N($D9)/$C9) | K9: =IF(N($D9)=0,"",N($E9)/$D9)
G10: =IF($B10="","",IFERROR(INDEX('商品'!$C$4:$C$18,MATCH($B10,'商品'!$A$4:$A$18,0)),"")) | H10: =IF(OR($B10="",$G10=""),"",$G10*(N($D10)-N($F10))) | I10: =IF($H10="","",$H10*'設定'!$C$4) | J10: =IF(N($C10)=0,"",N($D10)/$C10) | K10: =IF(N($D10)=0,"",N($E10)/$D10)
G11: =IF($B11="","",IFERROR(INDEX('商品'!$C$4:$C$18,MATCH($B11,'商品'!$A$4:$A$18,0)),"")) | H11: =IF(OR($B11="",$G11=""),"",$G11*(N($D11)-N($F11))) | I11: =IF($H11="","",$H11*'設定'!$C$4) | J11: =IF(N($C11)=0,"",N($D11)/$C11) | K11: =IF(N($D11)=0,"",N($E11)/$D11)
G12: =IF($B12="","",IFERROR(INDEX('商品'!$C$4:$C$18,MATCH($B12,'商品'!$A$4:$A$18,0)),"")) | H12: =IF(OR($B12="",$G12=""),"",$G12*(N($D12)-N($F12))) | I12: =IF($H12="","",$H12*'設定'!$C$4) | J12: =IF(N($C12)=0,"",N($D12)/$C12) | K12: =IF(N($D12)=0,"",N($E12)/$D12)
G13: =IF($B13="","",IFERROR(INDEX('商品'!$C$4:$C$18,MATCH($B13,'商品'!$A$4:$A$18,0)),"")) | H13: =IF(OR($B13="",$G13=""),"",$G13*(N($D13)-N($F13))) | I13: =IF($H13="","",$H13*'設定'!$C$4) | J13: =IF(N($C13)=0,"",N($D13)/$C13) | K13: =IF(N($D13)=0,"",N($E13)/$D13)
G14: =IF($B14="","",IFERROR(INDEX('商品'!$C$4:$C$18,MATCH($B14,'商品'!$A$4:$A$18,0)),"")) | H14: =IF(OR($B14="",$G14=""),"",$G14*(N($D14)-N($F14))) | I14: =IF($H14="","",$H14*'設定'!$C$4) | J14: =IF(N($C14)=0,"",N($D14)/$C14) | K14: =IF(N($D14)=0,"",N($E14)/$D14)
G15: =IF($B15="","",IFERROR(INDEX('商品'!$C$4:$C$18,MATCH($B15,'商品'!$A$4:$A$18,0)),"")) | H15: =IF(OR($B15="",$G15=""),"",$G15*(N($D15)-N($F15))) | I15: =IF($H15="","",$H15*'設定'!$C$4) | J15: =IF(N($C15)=0,"",N($D15)/$C15) | K15: =IF(N($D15)=0,"",N($E15)/$D15)
G16: =IF($B16="","",IFERROR(INDEX('商品'!$C$4:$C$18,MATCH($B16,'商品'!$A$4:$A$18,0)),"")) | H16: =IF(OR($B16="",$G16=""),"",$G16*(N($D16)-N($F16))) | I16: =IF($H16="","",$H16*'設定'!$C$4) | J16: =IF(N($C16)=0,"",N($D16)/$C16) | K16: =IF(N($D16)=0,"",N($E16)/$D16)
G17: =IF($B17="","",IFERROR(INDEX('商品'!$C$4:$C$18,MATCH($B17,'商品'!$A$4:$A$18,0)),"")) | H17: =IF(OR($B17="",$G17=""),"",$G17*(N($D17)-N($F17))) | I17: =IF($H17="","",$H17*'設定'!$C$4) | J17: =IF(N($C17)=0,"",N($D17)/$C17) | K17: =IF(N($D17)=0,"",N($E17)/$D17)
... G504: =IF($B504="","",IFERROR(INDEX('商品'!$C$4:$C$18,MATCH($B504,'商品'!$A$4:$A$18,0)),"")) | H504: =IF(OR($B504="",$G504=""),"",$G504*(N($D504)-N($F504))) | I504: =IF($H504="","",$H504*'設定'!$C$4) | J504: =IF(N($C504)=0,"",N($D504)/$C504) | K504: =IF(N($D504)=0,"",N($E504)/$D504)

Sheet 月次
A1: 月次の成績と、目標までの距離
A3: 月 | B3: フォロワー | C3: 全体ビュー | D3: メンバー数 | E3: メンバー 月額 | F3: 単品の売上 | G3: メンバーの売上 | H3: 売上合計 | I3: 手取り見込み | J3: 目標の達成率 | K3: 単品の購入数 | L3: 単品の購入率
A4: 46266 | E4: 1480 | F4: =SUMIFS('週次'!$H$5:$H$504,'週次'!$A$5:$A$504,">="&$A4,'週次'!$A$5:$A$504,"<"&EDATE($A4,1)) | G4: =N(D4)*N(E4) | H4: =F4+G4 | I4: =H4*'設定'!$C$4 | J4: =IF('設定'!$C$5>0,I4/'設定'!$C$5,0) | K4: =SUMIFS('週次'!$D$5:$D$504,'週次'!$A$5:$A$504,">="&$A4,'週次'!$A$5:$A$504,"<"&EDATE($A4,1)) | L4: =IFERROR(K4/SUMIFS('週次'!$C$5:$C$504,'週次'!$A$5:$A$504,">="&$A4,'週次'!$A$5:$A$504,"<"&EDATE($A4,1)),"")
A5: =EDATE(A4,1) | E5: 1480 | F5: =SUMIFS('週次'!$H$5:$H$504,'週次'!$A$5:$A$504,">="&$A5,'週次'!$A$5:$A$504,"<"&EDATE($A5,1)) | G5: =N(D5)*N(E5) | H5: =F5+G5 | I5: =H5*'設定'!$C$4 | J5: =IF('設定'!$C$5>0,I5/'設定'!$C$5,0) | K5: =SUMIFS('週次'!$D$5:$D$504,'週次'!$A$5:$A$504,">="&$A5,'週次'!$A$5:$A$504,"<"&EDATE($A5,1)) | L5: =IFERROR(K5/SUMIFS('週次'!$C$5:$C$504,'週次'!$A$5:$A$504,">="&$A5,'週次'!$A$5:$A$504,"<"&EDATE($A5,1)),"")
A6: =EDATE(A5,1) | E6: 1480 | F6: =SUMIFS('週次'!$H$5:$H$504,'週次'!$A$5:$A$504,">="&$A6,'週次'!$A$5:$A$504,"<"&EDATE($A6,1)) | G6: =N(D6)*N(E6) | H6: =F6+G6 | I6: =H6*'設定'!$C$4 | J6: =IF('設定'!$C$5>0,I6/'設定'!$C$5,0) | K6: =SUMIFS('週次'!$D$5:$D$504,'週次'!$A$5:$A$504,">="&$A6,'週次'!$A$5:$A$504,"<"&EDATE($A6,1)) | L6: =IFERROR(K6/SUMIFS('週次'!$C$5:$C$504,'週次'!$A$5:$A$504,">="&$A6,'週次'!$A$5:$A$504,"<"&EDATE($A6,1)),"")
A7: =EDATE(A6,1) | E7: 1480 | F7: =SUMIFS('週次'!$H$5:$H$504,'週次'!$A$5:$A$504,">="&$A7,'週次'!$A$5:$A$504,"<"&EDATE($A7,1)) | G7: =N(D7)*N(E7) | H7: =F7+G7 | I7: =H7*'設定'!$C$4 | J7: =IF('設定'!$C$5>0,I7/'設定'!$C$5,0) | K7: =SUMIFS('週次'!$D$5:$D$504,'週次'!$A$5:$A$504,">="&$A7,'週次'!$A$5:$A$504,"<"&EDATE($A7,1)) | L7: =IFERROR(K7/SUMIFS('週次'!$C$5:$C$504,'週次'!$A$5:$A$504,">="&$A7,'週次'!$A$5:$A$504,"<"&EDATE($A7,1)),"")
A8: =EDATE(A7,1) | E8: 1480 | F8: =SUMIFS('週次'!$H$5:$H$504,'週次'!$A$5:$A$504,">="&$A8,'週次'!$A$5:$A$504,"<"&EDATE($A8,1)) | G8: =N(D8)*N(E8) | H8: =F8+G8 | I8: =H8*'設定'!$C$4 | J8: =IF('設定'!$C$5>0,I8/'設定'!$C$5,0) | K8: =SUMIFS('週次'!$D$5:$D$504,'週次'!$A$5:$A$504,">="&$A8,'週次'!$A$5:$A$504,"<"&EDATE($A8,1)) | L8: =IFERROR(K8/SUMIFS('週次'!$C$5:$C$504,'週次'!$A$5:$A$504,">="&$A8,'週次'!$A$5:$A$504,"<"&EDATE($A8,1)),"")
A9: =EDATE(A8,1) | E9: 1480 | F9: =SUMIFS('週次'!$H$5:$H$504,'週次'!$A$5:$A$504,">="&$A9,'週次'!$A$5:$A$504,"<"&EDATE($A9,1)) | G9: =N(D9)*N(E9) | H9: =F9+G9 | I9: =H9*'設定'!$C$4 | J9: =IF('設定'!$C$5>0,I9/'設定'!$C$5,0) | K9: =SUMIFS('週次'!$D$5:$D$504,'週次'!$A$5:$A$504,">="&$A9,'週次'!$A$5:$A$504,"<"&EDATE($A9,1)) | L9: =IFERROR(K9/SUMIFS('週次'!$C$5:$C$504,'週次'!$A$5:$A$504,">="&$A9,'週次'!$A$5:$A$504,"<"&EDATE($A9,1)),"")
A10: =EDATE(A9,1) | E10: 1480 | F10: =SUMIFS('週次'!$H$5:$H$504,'週次'!$A$5:$A$504,">="&$A10,'週次'!$A$5:$A$504,"<"&EDATE($A10,1)) | G10: =N(D10)*N(E10) | H10: =F10+G10 | I10: =H10*'設定'!$C$4 | J10: =IF('設定'!$C$5>0,I10/'設定'!$C$5,0) | K10: =SUMIFS('週次'!$D$5:$D$504,'週次'!$A$5:$A$504,">="&$A10,'週次'!$A$5:$A$504,"<"&EDATE($A10,1)) | L10: =IFERROR(K10/SUMIFS('週次'!$C$5:$C$504,'週次'!$A$5:$A$504,">="&$A10,'週次'!$A$5:$A$504,"<"&EDATE($A10,1)),"")
A11: =EDATE(A10,1) | E11: 1480 | F11: =SUMIFS('週次'!$H$5:$H$504,'週次'!$A$5:$A$504,">="&$A11,'週次'!$A$5:$A$504,"<"&EDATE($A11,1)) | G11: =N(D11)*N(E11) | H11: =F11+G11 | I11: =H11*'設定'!$C$4 | J11: =IF('設定'!$C$5>0,I11/'設定'!$C$5,0) | K11: =SUMIFS('週次'!$D$5:$D$504,'週次'!$A$5:$A$504,">="&$A11,'週次'!$A$5:$A$504,"<"&EDATE($A11,1)) | L11: =IFERROR(K11/SUMIFS('週次'!$C$5:$C$504,'週次'!$A$5:$A$504,">="&$A11,'週次'!$A$5:$A$504,"<"&EDATE($A11,1)),"")
A12: =EDATE(A11,1) | E12: 1480 | F12: =SUMIFS('週次'!$H$5:$H$504,'週次'!$A$5:$A$504,">="&$A12,'週次'!$A$5:$A$504,"<"&EDATE($A12,1)) | G12: =N(D12)*N(E12) | H12: =F12+G12 | I12: =H12*'設定'!$C$4 | J12: =IF('設定'!$C$5>0,I12/'設定'!$C$5,0) | K12: =SUMIFS('週次'!$D$5:$D$504,'週次'!$A$5:$A$504,">="&$A12,'週次'!$A$5:$A$504,"<"&EDATE($A12,1)) | L12: =IFERROR(K12/SUMIFS('週次'!$C$5:$C$504,'週次'!$A$5:$A$504,">="&$A12,'週次'!$A$5:$A$504,"<"&EDATE($A12,1)),"")
A13: =EDATE(A12,1) | E13: 1480 | F13: =SUMIFS('週次'!$H$5:$H$504,'週次'!$A$5:$A$504,">="&$A13,'週次'!$A$5:$A$504,"<"&EDATE($A13,1)) | G13: =N(D13)*N(E13) | H13: =F13+G13 | I13: =H13*'設定'!$C$4 | J13: =IF('設定'!$C$5>0,I13/'設定'!$C$5,0) | K13: =SUMIFS('週次'!$D$5:$D$504,'週次'!$A$5:$A$504,">="&$A13,'週次'!$A$5:$A$504,"<"&EDATE($A13,1)) | L13: =IFERROR(K13/SUMIFS('週次'!$C$5:$C$504,'週次'!$A$5:$A$504,">="&$A13,'週次'!$A$5:$A$504,"<"&EDATE($A13,1)),"")
A14: =EDATE(A13,1) | E14: 1480 | F14: =SUMIFS('週次'!$H$5:$H$504,'週次'!$A$5:$A$504,">="&$A14,'週次'!$A$5:$A$504,"<"&EDATE($A14,1)) | G14: =N(D14)*N(E14) | H14: =F14+G14 | I14: =H14*'設定'!$C$4 | J14: =IF('設定'!$C$5>0,I14/'設定'!$C$5,0) | K14: =SUMIFS('週次'!$D$5:$D$504,'週次'!$A$5:$A$504,">="&$A14,'週次'!$A$5:$A$504,"<"&EDATE($A14,1)) | L14: =IFERROR(K14/SUMIFS('週次'!$C$5:$C$504,'週次'!$A$5:$A$504,">="&$A14,'週次'!$A$5:$A$504,"<"&EDATE($A14,1)),"")
A15: =EDATE(A14,1) | E15: 1480 | F15: =SUMIFS('週次'!$H$5:$H$504,'週次'!$A$5:$A$504,">="&$A15,'週次'!$A$5:$A$504,"<"&EDATE($A15,1)) | G15: =N(D15)*N(E15) | H15: =F15+G15 | I15: =H15*'設定'!$C$4 | J15: =IF('設定'!$C$5>0,I15/'設定'!$C$5,0) | K15: =SUMIFS('週次'!$D$5:$D$504,'週次'!$A$5:$A$504,">="&$A15,'週次'!$A$5:$A$504,"<"&EDATE($A15,1)) | L15: =IFERROR(K15/SUMIFS('週次'!$C$5:$C$504,'週次'!$A$5:$A$504,">="&$A15,'週次'!$A$5:$A$504,"<"&EDATE($A15,1)),"")
A16: =EDATE(A15,1) | E16: 1480 | F16: =SUMIFS('週次'!$H$5:$H$504,'週次'!$A$5:$A$504,">="&$A16,'週次'!$A$5:$A$504,"<"&EDATE($A16,1)) | G16: =N(D16)*N(E16) | H16: =F16+G16 | I16: =H16*'設定'!$C$4 | J16: =IF('設定'!$C$5>0,I16/'設定'!$C$5,0) | K16: =SUMIFS('週次'!$D$5:$D$504,'週次'!$A$5:$A$504,">="&$A16,'週次'!$A$5:$A$504,"<"&EDATE($A16,1)) | L16: =IFERROR(K16/SUMIFS('週次'!$C$5:$C$504,'週次'!$A$5:$A$504,">="&$A16,'週次'!$A$5:$A$504,"<"&EDATE($A16,1)),"")
... A21: =EDATE(A20,1) | E21: 1480 | F21: =SUMIFS('週次'!$H$5:$H$504,'週次'!$A$5:$A$504,">="&$A21,'週次'!$A$5:$A$504,"<"&EDATE($A21,1)) | G21: =N(D21)*N(E21) | H21: =F21+G21 | I21: =H21*'設定'!$C$4 | J21: =IF('設定'!$C$5>0,I21/'設定'!$C$5,0) | K21: =SUMIFS('週次'!$D$5:$D$504,'週次'!$A$5:$A$504,">="&$A21,'週次'!$A$5:$A$504,"<"&EDATE($A21,1)) | L21: =IFERROR(K21/SUMIFS('週次'!$C$5:$C$504,'週次'!$A$5:$A$504,">="&$A21,'週次'!$A$5:$A$504,"<"&EDATE($A21,1)),"")
A23: 週の開始日がその月に入る週を、その月の売上として数える。メンバーの売上は、メンバー数×月額の概算。
