Workbook

Sheet 使い方
A1: 買取せどり 仕入れ判定・入金管理シート
A3: 入力するのは黄色のセル（青い文字）だけです。灰色の見出しの列と、集計シートは自動で計算されます。
A5: 1. 設定シート：最低利益・最低利益率・送料／1箱・下落シナリオを、自分の基準に合わせる
A6: 2. 仕入れ判定シート：仕入れる前に、仕入れ価格と買取価格を入れて「判定」を見る
A7: ・同じ箱で送る商品には同じ箱ID（例：A1）を付ける。送料が点数で自動的に割られる（状態が「見送り」の行は点数に数えない）
A8: ・「OK・下落に弱い」は、買取価格が下落シナリオ分下がると赤字になる商品。点数を控えるか、すぐ発送する
A9: ・ポイントは判定に入れない（付与の時期・上限があるため）。別枠の列で確認する
A10: 3. 仕入れたら「状態」を 未発送 → 発送済 → 査定済 → 入金済 と更新し、確定買取額と日付を入れる
A11: ・状態が空欄の行は「判定しただけの候補」として、集計に数えない。見送った商品は「見送り」にしておくと後で見返せる
A12: 4. 集計シート：立て替えている現金、月別の見込み利益と確定利益、買取店別の減額率を確認する
A14: 判定のルール
A15: 仕入れOK：見込み利益 ≥ 最低利益、かつ 利益率 ≥ 最低利益率、かつ 下落時利益 ≥ 0
... A22: ・初期値の基準（利益500円・利益率15%・送料600円/箱）は運営者の実際の設定です。自分の送料・資金に合わせて変えてください

Sheet 設定
A1: 判定基準の設定
A2: 黄色のセルだけ書き換えてください。変えると全シートの判定が変わります。
B4: 最低利益（円） | C4: 500 | D4: 1件あたり、これ未満の利益なら見送る。初期値は運営者の実際の基準。
B5: 最低利益率 | C5: 0.15 | D5: 利益 ÷ 仕入れ価格。これ未満なら見送る。初期値は運営者の実際の基準。
B6: 送料／1箱（円） | C6: 600 | D6: 箱ごとに違う場合は、仕入れ判定シートの「箱の送料」列に入れると優先される。
B7: 買取価格の下落シナリオ | C7: 0.1 | D7: 発送から査定までに買取価格がこの割合だけ下がったときの利益を併記する。

Sheet 仕入れ判定
A1: 仕入れ判定・入金管理
A2: 緑の見出し＝入力する列／灰色の見出し＝自動計算。同じ箱で送る商品には同じ「箱ID」を付けると、送料が点数で自動的に割られます。
A3: 【例】の3行は見本です（同梱で送料が割られる例と、利益率不足で見送る例）。使い始めるときは行ごと消すか、上書きしてください。
A5: 仕入れ日 | B5: 商品名 | C5: JAN | D5: 仕入れ先 | E5: 買取店 | F5: 箱ID | G5: 仕入れ価格 （支払額） | H5: ポイント 還元率 | I5: 買取価格 （提示額） | J5: その他 コスト | K5: 箱の送料 （空欄=設定値） | L5: 同梱点数 | M5: 1点あたり 送料 | N5: 見込み利益 | O5: 利益率 | P5: ポイント （別枠） | Q5: 下落時 利益 | R5: 判定 | S5: 状態 | T5: 発送日 | U5: 確定 買取額 | V5: 入金日 | W5: 確定利益 | X5: 減額 | Y5: 発送→入金 日数 | Z5: 仕入れ済み | AA5: 確定済み
A6: 46296 | B6: 【例】ゲームソフトA | C6: 4900000000001 | D6: 楽天市場 | E6: 買取店X | F6: A1 | G6: 3800 | H6: 0.05 | I6: 5000 | J6: 0 | L6: =IF($G6="","",IF($F6="",1,MAX(1,COUNTIF($F$6:$F$505,$F6)-COUNTIFS($F$6:$F$505,$F6,$S$6:$S$505,"見送り")))) | M6: =IF($G6="","",IF($K6="",'設定'!$C$6,$K6)/$L6) | N6: =IF(OR($G6="",$I6=""),"",$I6-$G6-$M6-$J6) | O6: =IF($N6="","",IF($G6>0,$N6/$G6,0)) | P6: =IF($G6="","",$G6*$H6) | Q6: =IF($N6="","",$N6-$I6*'設定'!$C$7) | R6: =IF($N6="","",IF(AND($N6>='設定'!$C$4,$O6>='設定'!$C$5),IF($Q6>=0,"仕入れOK","OK・下落に弱い"),"見送り")) | S6: 未発送 | W6: =IF(OR($G6="",$U6=""),"",$U6-$G6-$M6-$J6) | X6: =IF(OR($I6="",$U6=""),"",$I6-$U6) | Y6: =IF(OR($T6="",$V6=""),"",$V6-$T6) | Z6: =IF(OR($S6="未発送",$S6="発送済",$S6="査定済",$S6="入金済"),1,0) | AA6: =IF($U6="",0,1)
A7: 46296 | B7: 【例】イヤホンB | C7: 4900000000002 | D7: Yahoo! | E7: 買取店X | F7: A1 | G7: 9200 | H7: 0.1 | I7: 10500 | J7: 0 | L7: =IF($G7="","",IF($F7="",1,MAX(1,COUNTIF($F$6:$F$505,$F7)-COUNTIFS($F$6:$F$505,$F7,$S$6:$S$505,"見送り")))) | M7: =IF($G7="","",IF($K7="",'設定'!$C$6,$K7)/$L7) | N7: =IF(OR($G7="",$I7=""),"",$I7-$G7-$M7-$J7) | O7: =IF($N7="","",IF($G7>0,$N7/$G7,0)) | P7: =IF($G7="","",$G7*$H7) | Q7: =IF($N7="","",$N7-$I7*'設定'!$C$7) | R7: =IF($N7="","",IF(AND($N7>='設定'!$C$4,$O7>='設定'!$C$5),IF($Q7>=0,"仕入れOK","OK・下落に弱い"),"見送り")) | S7: 見送り | W7: =IF(OR($G7="",$U7=""),"",$U7-$G7-$M7-$J7) | X7: =IF(OR($I7="",$U7=""),"",$I7-$U7) | Y7: =IF(OR($T7="",$V7=""),"",$V7-$T7) | Z7: =IF(OR($S7="未発送",$S7="発送済",$S7="査定済",$S7="入金済"),1,0) | AA7: =IF($U7="",0,1)
A8: 46297 | B8: 【例】周辺機器C | C8: 4900000000003 | D8: Amazon | E8: 買取店X | F8: A1 | G8: 2400 | H8: 0.01 | I8: 3200 | J8: 0 | L8: =IF($G8="","",IF($F8="",1,MAX(1,COUNTIF($F$6:$F$505,$F8)-COUNTIFS($F$6:$F$505,$F8,$S$6:$S$505,"見送り")))) | M8: =IF($G8="","",IF($K8="",'設定'!$C$6,$K8)/$L8) | N8: =IF(OR($G8="",$I8=""),"",$I8-$G8-$M8-$J8) | O8: =IF($N8="","",IF($G8>0,$N8/$G8,0)) | P8: =IF($G8="","",$G8*$H8) | Q8: =IF($N8="","",$N8-$I8*'設定'!$C$7) | R8: =IF($N8="","",IF(AND($N8>='設定'!$C$4,$O8>='設定'!$C$5),IF($Q8>=0,"仕入れOK","OK・下落に弱い"),"見送り")) | S8: 未発送 | W8: =IF(OR($G8="",$U8=""),"",$U8-$G8-$M8-$J8) | X8: =IF(OR($I8="",$U8=""),"",$I8-$U8) | Y8: =IF(OR($T8="",$V8=""),"",$V8-$T8) | Z8: =IF(OR($S8="未発送",$S8="発送済",$S8="査定済",$S8="入金済"),1,0) | AA8: =IF($U8="",0,1)
L9: =IF($G9="","",IF($F9="",1,MAX(1,COUNTIF($F$6:$F$505,$F9)-COUNTIFS($F$6:$F$505,$F9,$S$6:$S$505,"見送り")))) | M9: =IF($G9="","",IF($K9="",'設定'!$C$6,$K9)/$L9) | N9: =IF(OR($G9="",$I9=""),"",$I9-$G9-$M9-$J9) | O9: =IF($N9="","",IF($G9>0,$N9/$G9,0)) | P9: =IF($G9="","",$G9*$H9) | Q9: =IF($N9="","",$N9-$I9*'設定'!$C$7) | R9: =IF($N9="","",IF(AND($N9>='設定'!$C$4,$O9>='設定'!$C$5),IF($Q9>=0,"仕入れOK","OK・下落に弱い"),"見送り")) | W9: =IF(OR($G9="",$U9=""),"",$U9-$G9-$M9-$J9) | X9: =IF(OR($I9="",$U9=""),"",$I9-$U9) | Y9: =IF(OR($T9="",$V9=""),"",$V9-$T9) | Z9: =IF(OR($S9="未発送",$S9="発送済",$S9="査定済",$S9="入金済"),1,0) | AA9: =IF($U9="",0,1)
L10: =IF($G10="","",IF($F10="",1,MAX(1,COUNTIF($F$6:$F$505,$F10)-COUNTIFS($F$6:$F$505,$F10,$S$6:$S$505,"見送り")))) | M10: =IF($G10="","",IF($K10="",'設定'!$C$6,$K10)/$L10) | N10: =IF(OR($G10="",$I10=""),"",$I10-$G10-$M10-$J10) | O10: =IF($N10="","",IF($G10>0,$N10/$G10,0)) | P10: =IF($G10="","",$G10*$H10) | Q10: =IF($N10="","",$N10-$I10*'設定'!$C$7) | R10: =IF($N10="","",IF(AND($N10>='設定'!$C$4,$O10>='設定'!$C$5),IF($Q10>=0,"仕入れOK","OK・下落に弱い"),"見送り")) | W10: =IF(OR($G10="",$U10=""),"",$U10-$G10-$M10-$J10) | X10: =IF(OR($I10="",$U10=""),"",$I10-$U10) | Y10: =IF(OR($T10="",$V10=""),"",$V10-$T10) | Z10: =IF(OR($S10="未発送",$S10="発送済",$S10="査定済",$S10="入金済"),1,0) | AA10: =IF($U10="",0,1)
L11: =IF($G11="","",IF($F11="",1,MAX(1,COUNTIF($F$6:$F$505,$F11)-COUNTIFS($F$6:$F$505,$F11,$S$6:$S$505,"見送り")))) | M11: =IF($G11="","",IF($K11="",'設定'!$C$6,$K11)/$L11) | N11: =IF(OR($G11="",$I11=""),"",$I11-$G11-$M11-$J11) | O11: =IF($N11="","",IF($G11>0,$N11/$G11,0)) | P11: =IF($G11="","",$G11*$H11) | Q11: =IF($N11="","",$N11-$I11*'設定'!$C$7) | R11: =IF($N11="","",IF(AND($N11>='設定'!$C$4,$O11>='設定'!$C$5),IF($Q11>=0,"仕入れOK","OK・下落に弱い"),"見送り")) | W11: =IF(OR($G11="",$U11=""),"",$U11-$G11-$M11-$J11) | X11: =IF(OR($I11="",$U11=""),"",$I11-$U11) | Y11: =IF(OR($T11="",$V11=""),"",$V11-$T11) | Z11: =IF(OR($S11="未発送",$S11="発送済",$S11="査定済",$S11="入金済"),1,0) | AA11: =IF($U11="",0,1)
L12: =IF($G12="","",IF($F12="",1,MAX(1,COUNTIF($F$6:$F$505,$F12)-COUNTIFS($F$6:$F$505,$F12,$S$6:$S$505,"見送り")))) | M12: =IF($G12="","",IF($K12="",'設定'!$C$6,$K12)/$L12) | N12: =IF(OR($G12="",$I12=""),"",$I12-$G12-$M12-$J12) | O12: =IF($N12="","",IF($G12>0,$N12/$G12,0)) | P12: =IF($G12="","",$G12*$H12) | Q12: =IF($N12="","",$N12-$I12*'設定'!$C$7) | R12: =IF($N12="","",IF(AND($N12>='設定'!$C$4,$O12>='設定'!$C$5),IF($Q12>=0,"仕入れOK","OK・下落に弱い"),"見送り")) | W12: =IF(OR($G12="",$U12=""),"",$U12-$G12-$M12-$J12) | X12: =IF(OR($I12="",$U12=""),"",$I12-$U12) | Y12: =IF(OR($T12="",$V12=""),"",$V12-$T12) | Z12: =IF(OR($S12="未発送",$S12="発送済",$S12="査定済",$S12="入金済"),1,0) | AA12: =IF($U12="",0,1)
L13: =IF($G13="","",IF($F13="",1,MAX(1,COUNTIF($F$6:$F$505,$F13)-COUNTIFS($F$6:$F$505,$F13,$S$6:$S$505,"見送り")))) | M13: =IF($G13="","",IF($K13="",'設定'!$C$6,$K13)/$L13) | N13: =IF(OR($G13="",$I13=""),"",$I13-$G13-$M13-$J13) | O13: =IF($N13="","",IF($G13>0,$N13/$G13,0)) | P13: =IF($G13="","",$G13*$H13) | Q13: =IF($N13="","",$N13-$I13*'設定'!$C$7) | R13: =IF($N13="","",IF(AND($N13>='設定'!$C$4,$O13>='設定'!$C$5),IF($Q13>=0,"仕入れOK","OK・下落に弱い"),"見送り")) | W13: =IF(OR($G13="",$U13=""),"",$U13-$G13-$M13-$J13) | X13: =IF(OR($I13="",$U13=""),"",$I13-$U13) | Y13: =IF(OR($T13="",$V13=""),"",$V13-$T13) | Z13: =IF(OR($S13="未発送",$S13="発送済",$S13="査定済",$S13="入金済"),1,0) | AA13: =IF($U13="",0,1)
L14: =IF($G14="","",IF($F14="",1,MAX(1,COUNTIF($F$6:$F$505,$F14)-COUNTIFS($F$6:$F$505,$F14,$S$6:$S$505,"見送り")))) | M14: =IF($G14="","",IF($K14="",'設定'!$C$6,$K14)/$L14) | N14: =IF(OR($G14="",$I14=""),"",$I14-$G14-$M14-$J14) | O14: =IF($N14="","",IF($G14>0,$N14/$G14,0)) | P14: =IF($G14="","",$G14*$H14) | Q14: =IF($N14="","",$N14-$I14*'設定'!$C$7) | R14: =IF($N14="","",IF(AND($N14>='設定'!$C$4,$O14>='設定'!$C$5),IF($Q14>=0,"仕入れOK","OK・下落に弱い"),"見送り")) | W14: =IF(OR($G14="",$U14=""),"",$U14-$G14-$M14-$J14) | X14: =IF(OR($I14="",$U14=""),"",$I14-$U14) | Y14: =IF(OR($T14="",$V14=""),"",$V14-$T14) | Z14: =IF(OR($S14="未発送",$S14="発送済",$S14="査定済",$S14="入金済"),1,0) | AA14: =IF($U14="",0,1)
L15: =IF($G15="","",IF($F15="",1,MAX(1,COUNTIF($F$6:$F$505,$F15)-COUNTIFS($F$6:$F$505,$F15,$S$6:$S$505,"見送り")))) | M15: =IF($G15="","",IF($K15="",'設定'!$C$6,$K15)/$L15) | N15: =IF(OR($G15="",$I15=""),"",$I15-$G15-$M15-$J15) | O15: =IF($N15="","",IF($G15>0,$N15/$G15,0)) | P15: =IF($G15="","",$G15*$H15) | Q15: =IF($N15="","",$N15-$I15*'設定'!$C$7) | R15: =IF($N15="","",IF(AND($N15>='設定'!$C$4,$O15>='設定'!$C$5),IF($Q15>=0,"仕入れOK","OK・下落に弱い"),"見送り")) | W15: =IF(OR($G15="",$U15=""),"",$U15-$G15-$M15-$J15) | X15: =IF(OR($I15="",$U15=""),"",$I15-$U15) | Y15: =IF(OR($T15="",$V15=""),"",$V15-$T15) | Z15: =IF(OR($S15="未発送",$S15="発送済",$S15="査定済",$S15="入金済"),1,0) | AA15: =IF($U15="",0,1)
L16: =IF($G16="","",IF($F16="",1,MAX(1,COUNTIF($F$6:$F$505,$F16)-COUNTIFS($F$6:$F$505,$F16,$S$6:$S$505,"見送り")))) | M16: =IF($G16="","",IF($K16="",'設定'!$C$6,$K16)/$L16) | N16: =IF(OR($G16="",$I16=""),"",$I16-$G16-$M16-$J16) | O16: =IF($N16="","",IF($G16>0,$N16/$G16,0)) | P16: =IF($G16="","",$G16*$H16) | Q16: =IF($N16="","",$N16-$I16*'設定'!$C$7) | R16: =IF($N16="","",IF(AND($N16>='設定'!$C$4,$O16>='設定'!$C$5),IF($Q16>=0,"仕入れOK","OK・下落に弱い"),"見送り")) | W16: =IF(OR($G16="",$U16=""),"",$U16-$G16-$M16-$J16) | X16: =IF(OR($I16="",$U16=""),"",$I16-$U16) | Y16: =IF(OR($T16="",$V16=""),"",$V16-$T16) | Z16: =IF(OR($S16="未発送",$S16="発送済",$S16="査定済",$S16="入金済"),1,0) | AA16: =IF($U16="",0,1)
L17: =IF($G17="","",IF($F17="",1,MAX(1,COUNTIF($F$6:$F$505,$F17)-COUNTIFS($F$6:$F$505,$F17,$S$6:$S$505,"見送り")))) | M17: =IF($G17="","",IF($K17="",'設定'!$C$6,$K17)/$L17) | N17: =IF(OR($G17="",$I17=""),"",$I17-$G17-$M17-$J17) | O17: =IF($N17="","",IF($G17>0,$N17/$G17,0)) | P17: =IF($G17="","",$G17*$H17) | Q17: =IF($N17="","",$N17-$I17*'設定'!$C$7) | R17: =IF($N17="","",IF(AND($N17>='設定'!$C$4,$O17>='設定'!$C$5),IF($Q17>=0,"仕入れOK","OK・下落に弱い"),"見送り")) | W17: =IF(OR($G17="",$U17=""),"",$U17-$G17-$M17-$J17) | X17: =IF(OR($I17="",$U17=""),"",$I17-$U17) | Y17: =IF(OR($T17="",$V17=""),"",$V17-$T17) | Z17: =IF(OR($S17="未発送",$S17="発送済",$S17="査定済",$S17="入金済"),1,0) | AA17: =IF($U17="",0,1)
L18: =IF($G18="","",IF($F18="",1,MAX(1,COUNTIF($F$6:$F$505,$F18)-COUNTIFS($F$6:$F$505,$F18,$S$6:$S$505,"見送り")))) | M18: =IF($G18="","",IF($K18="",'設定'!$C$6,$K18)/$L18) | N18: =IF(OR($G18="",$I18=""),"",$I18-$G18-$M18-$J18) | O18: =IF($N18="","",IF($G18>0,$N18/$G18,0)) | P18: =IF($G18="","",$G18*$H18) | Q18: =IF($N18="","",$N18-$I18*'設定'!$C$7) | R18: =IF($N18="","",IF(AND($N18>='設定'!$C$4,$O18>='設定'!$C$5),IF($Q18>=0,"仕入れOK","OK・下落に弱い"),"見送り")) | W18: =IF(OR($G18="",$U18=""),"",$U18-$G18-$M18-$J18) | X18: =IF(OR($I18="",$U18=""),"",$I18-$U18) | Y18: =IF(OR($T18="",$V18=""),"",$V18-$T18) | Z18: =IF(OR($S18="未発送",$S18="発送済",$S18="査定済",$S18="入金済"),1,0) | AA18: =IF($U18="",0,1)
L19: =IF($G19="","",IF($F19="",1,MAX(1,COUNTIF($F$6:$F$505,$F19)-COUNTIFS($F$6:$F$505,$F19,$S$6:$S$505,"見送り")))) | M19: =IF($G19="","",IF($K19="",'設定'!$C$6,$K19)/$L19) | N19: =IF(OR($G19="",$I19=""),"",$I19-$G19-$M19-$J19) | O19: =IF($N19="","",IF($G19>0,$N19/$G19,0)) | P19: =IF($G19="","",$G19*$H19) | Q19: =IF($N19="","",$N19-$I19*'設定'!$C$7) | R19: =IF($N19="","",IF(AND($N19>='設定'!$C$4,$O19>='設定'!$C$5),IF($Q19>=0,"仕入れOK","OK・下落に弱い"),"見送り")) | W19: =IF(OR($G19="",$U19=""),"",$U19-$G19-$M19-$J19) | X19: =IF(OR($I19="",$U19=""),"",$I19-$U19) | Y19: =IF(OR($T19="",$V19=""),"",$V19-$T19) | Z19: =IF(OR($S19="未発送",$S19="発送済",$S19="査定済",$S19="入金済"),1,0) | AA19: =IF($U19="",0,1)
L20: =IF($G20="","",IF($F20="",1,MAX(1,COUNTIF($F$6:$F$505,$F20)-COUNTIFS($F$6:$F$505,$F20,$S$6:$S$505,"見送り")))) | M20: =IF($G20="","",IF($K20="",'設定'!$C$6,$K20)/$L20) | N20: =IF(OR($G20="",$I20=""),"",$I20-$G20-$M20-$J20) | O20: =IF($N20="","",IF($G20>0,$N20/$G20,0)) | P20: =IF($G20="","",$G20*$H20) | Q20: =IF($N20="","",$N20-$I20*'設定'!$C$7) | R20: =IF($N20="","",IF(AND($N20>='設定'!$C$4,$O20>='設定'!$C$5),IF($Q20>=0,"仕入れOK","OK・下落に弱い"),"見送り")) | W20: =IF(OR($G20="",$U20=""),"",$U20-$G20-$M20-$J20) | X20: =IF(OR($I20="",$U20=""),"",$I20-$U20) | Y20: =IF(OR($T20="",$V20=""),"",$V20-$T20) | Z20: =IF(OR($S20="未発送",$S20="発送済",$S20="査定済",$S20="入金済"),1,0) | AA20: =IF($U20="",0,1)
... L505: =IF($G505="","",IF($F505="",1,MAX(1,COUNTIF($F$6:$F$505,$F505)-COUNTIFS($F$6:$F$505,$F505,$S$6:$S$505,"見送り")))) | M505: =IF($G505="","",IF($K505="",'設定'!$C$6,$K505)/$L505) | N505: =IF(OR($G505="",$I505=""),"",$I505-$G505-$M505-$J505) | O505: =IF($N505="","",IF($G505>0,$N505/$G505,0)) | P505: =IF($G505="","",$G505*$H505) | Q505: =IF($N505="","",$N505-$I505*'設定'!$C$7) | R505: =IF($N505="","",IF(AND($N505>='設定'!$C$4,$O505>='設定'!$C$5),IF($Q505>=0,"仕入れOK","OK・下落に弱い"),"見送り")) | W505: =IF(OR($G505="",$U505=""),"",$U505-$G505-$M505-$J505) | X505: =IF(OR($I505="",$U505=""),"",$I505-$U505) | Y505: =IF(OR($T505="",$V505=""),"",$V505-$T505) | Z505: =IF(OR($S505="未発送",$S505="発送済",$S505="査定済",$S505="入金済"),1,0) | AA505: =IF($U505="",0,1)

Sheet 集計
A1: お金の流れと月別の成績
A3: いま立て替えている現金
A4: 仕入れ済みで未入金の支払額 | D4: =SUMIFS('仕入れ判定'!$G$6:$G$505,'仕入れ判定'!$S$6:$S$505,"未発送")+SUMIFS('仕入れ判定'!$G$6:$G$505,'仕入れ判定'!$S$6:$S$505,"発送済")+SUMIFS('仕入れ判定'!$G$6:$G$505,'仕入れ判定'!$S$6:$S$505,"査定済") | E4: カードの支払日までに、この金額が戻ってくるかを確認する。
A5: 入金待ちの見込み額（発送済は提示額、査定済は確定額） | D5: =SUMIFS('仕入れ判定'!$I$6:$I$505,'仕入れ判定'!$S$6:$S$505,"発送済")+SUMIFS('仕入れ判定'!$U$6:$U$505,'仕入れ判定'!$S$6:$S$505,"査定済")
A6: 未発送の点数 | D6: =COUNTIFS('仕入れ判定'!$S$6:$S$505,"未発送")
A9: 月別の成績（A列の月は書き換えてよい）
A10: 月 | B10: 仕入れ件数 | C10: 仕入れ額 | D10: 見込み利益 | E10: 確定利益 | F10: 減額合計 | G10: 確定利益率
A11: 46296 | B11: =SUMIFS('仕入れ判定'!$Z$6:$Z$505,'仕入れ判定'!$A$6:$A$505,">="&$A11,'仕入れ判定'!$A$6:$A$505,"<"&EDATE($A11,1)) | C11: =SUMIFS('仕入れ判定'!$G$6:$G$505,'仕入れ判定'!$A$6:$A$505,">="&$A11,'仕入れ判定'!$A$6:$A$505,"<"&EDATE($A11,1),'仕入れ判定'!$Z$6:$Z$505,1) | D11: =SUMIFS('仕入れ判定'!$N$6:$N$505,'仕入れ判定'!$A$6:$A$505,">="&$A11,'仕入れ判定'!$A$6:$A$505,"<"&EDATE($A11,1),'仕入れ判定'!$Z$6:$Z$505,1) | E11: =SUMIFS('仕入れ判定'!$W$6:$W$505,'仕入れ判定'!$A$6:$A$505,">="&$A11,'仕入れ判定'!$A$6:$A$505,"<"&EDATE($A11,1),'仕入れ判定'!$AA$6:$AA$505,1) | F11: =SUMIFS('仕入れ判定'!$X$6:$X$505,'仕入れ判定'!$A$6:$A$505,">="&$A11,'仕入れ判定'!$A$6:$A$505,"<"&EDATE($A11,1),'仕入れ判定'!$AA$6:$AA$505,1) | G11: =IFERROR(E11/SUMIFS('仕入れ判定'!$G$6:$G$505,'仕入れ判定'!$A$6:$A$505,">="&$A11,'仕入れ判定'!$A$6:$A$505,"<"&EDATE($A11,1),'仕入れ判定'!$AA$6:$AA$505,1),0)
A12: =EDATE(A11,1) | B12: =SUMIFS('仕入れ判定'!$Z$6:$Z$505,'仕入れ判定'!$A$6:$A$505,">="&$A12,'仕入れ判定'!$A$6:$A$505,"<"&EDATE($A12,1)) | C12: =SUMIFS('仕入れ判定'!$G$6:$G$505,'仕入れ判定'!$A$6:$A$505,">="&$A12,'仕入れ判定'!$A$6:$A$505,"<"&EDATE($A12,1),'仕入れ判定'!$Z$6:$Z$505,1) | D12: =SUMIFS('仕入れ判定'!$N$6:$N$505,'仕入れ判定'!$A$6:$A$505,">="&$A12,'仕入れ判定'!$A$6:$A$505,"<"&EDATE($A12,1),'仕入れ判定'!$Z$6:$Z$505,1) | E12: =SUMIFS('仕入れ判定'!$W$6:$W$505,'仕入れ判定'!$A$6:$A$505,">="&$A12,'仕入れ判定'!$A$6:$A$505,"<"&EDATE($A12,1),'仕入れ判定'!$AA$6:$AA$505,1) | F12: =SUMIFS('仕入れ判定'!$X$6:$X$505,'仕入れ判定'!$A$6:$A$505,">="&$A12,'仕入れ判定'!$A$6:$A$505,"<"&EDATE($A12,1),'仕入れ判定'!$AA$6:$AA$505,1) | G12: =IFERROR(E12/SUMIFS('仕入れ判定'!$G$6:$G$505,'仕入れ判定'!$A$6:$A$505,">="&$A12,'仕入れ判定'!$A$6:$A$505,"<"&EDATE($A12,1),'仕入れ判定'!$AA$6:$AA$505,1),0)
A13: =EDATE(A12,1) | B13: =SUMIFS('仕入れ判定'!$Z$6:$Z$505,'仕入れ判定'!$A$6:$A$505,">="&$A13,'仕入れ判定'!$A$6:$A$505,"<"&EDATE($A13,1)) | C13: =SUMIFS('仕入れ判定'!$G$6:$G$505,'仕入れ判定'!$A$6:$A$505,">="&$A13,'仕入れ判定'!$A$6:$A$505,"<"&EDATE($A13,1),'仕入れ判定'!$Z$6:$Z$505,1) | D13: =SUMIFS('仕入れ判定'!$N$6:$N$505,'仕入れ判定'!$A$6:$A$505,">="&$A13,'仕入れ判定'!$A$6:$A$505,"<"&EDATE($A13,1),'仕入れ判定'!$Z$6:$Z$505,1) | E13: =SUMIFS('仕入れ判定'!$W$6:$W$505,'仕入れ判定'!$A$6:$A$505,">="&$A13,'仕入れ判定'!$A$6:$A$505,"<"&EDATE($A13,1),'仕入れ判定'!$AA$6:$AA$505,1) | F13: =SUMIFS('仕入れ判定'!$X$6:$X$505,'仕入れ判定'!$A$6:$A$505,">="&$A13,'仕入れ判定'!$A$6:$A$505,"<"&EDATE($A13,1),'仕入れ判定'!$AA$6:$AA$505,1) | G13: =IFERROR(E13/SUMIFS('仕入れ判定'!$G$6:$G$505,'仕入れ判定'!$A$6:$A$505,">="&$A13,'仕入れ判定'!$A$6:$A$505,"<"&EDATE($A13,1),'仕入れ判定'!$AA$6:$AA$505,1),0)
A14: =EDATE(A13,1) | B14: =SUMIFS('仕入れ判定'!$Z$6:$Z$505,'仕入れ判定'!$A$6:$A$505,">="&$A14,'仕入れ判定'!$A$6:$A$505,"<"&EDATE($A14,1)) | C14: =SUMIFS('仕入れ判定'!$G$6:$G$505,'仕入れ判定'!$A$6:$A$505,">="&$A14,'仕入れ判定'!$A$6:$A$505,"<"&EDATE($A14,1),'仕入れ判定'!$Z$6:$Z$505,1) | D14: =SUMIFS('仕入れ判定'!$N$6:$N$505,'仕入れ判定'!$A$6:$A$505,">="&$A14,'仕入れ判定'!$A$6:$A$505,"<"&EDATE($A14,1),'仕入れ判定'!$Z$6:$Z$505,1) | E14: =SUMIFS('仕入れ判定'!$W$6:$W$505,'仕入れ判定'!$A$6:$A$505,">="&$A14,'仕入れ判定'!$A$6:$A$505,"<"&EDATE($A14,1),'仕入れ判定'!$AA$6:$AA$505,1) | F14: =SUMIFS('仕入れ判定'!$X$6:$X$505,'仕入れ判定'!$A$6:$A$505,">="&$A14,'仕入れ判定'!$A$6:$A$505,"<"&EDATE($A14,1),'仕入れ判定'!$AA$6:$AA$505,1) | G14: =IFERROR(E14/SUMIFS('仕入れ判定'!$G$6:$G$505,'仕入れ判定'!$A$6:$A$505,">="&$A14,'仕入れ判定'!$A$6:$A$505,"<"&EDATE($A14,1),'仕入れ判定'!$AA$6:$AA$505,1),0)
A15: =EDATE(A14,1) | B15: =SUMIFS('仕入れ判定'!$Z$6:$Z$505,'仕入れ判定'!$A$6:$A$505,">="&$A15,'仕入れ判定'!$A$6:$A$505,"<"&EDATE($A15,1)) | C15: =SUMIFS('仕入れ判定'!$G$6:$G$505,'仕入れ判定'!$A$6:$A$505,">="&$A15,'仕入れ判定'!$A$6:$A$505,"<"&EDATE($A15,1),'仕入れ判定'!$Z$6:$Z$505,1) | D15: =SUMIFS('仕入れ判定'!$N$6:$N$505,'仕入れ判定'!$A$6:$A$505,">="&$A15,'仕入れ判定'!$A$6:$A$505,"<"&EDATE($A15,1),'仕入れ判定'!$Z$6:$Z$505,1) | E15: =SUMIFS('仕入れ判定'!$W$6:$W$505,'仕入れ判定'!$A$6:$A$505,">="&$A15,'仕入れ判定'!$A$6:$A$505,"<"&EDATE($A15,1),'仕入れ判定'!$AA$6:$AA$505,1) | F15: =SUMIFS('仕入れ判定'!$X$6:$X$505,'仕入れ判定'!$A$6:$A$505,">="&$A15,'仕入れ判定'!$A$6:$A$505,"<"&EDATE($A15,1),'仕入れ判定'!$AA$6:$AA$505,1) | G15: =IFERROR(E15/SUMIFS('仕入れ判定'!$G$6:$G$505,'仕入れ判定'!$A$6:$A$505,">="&$A15,'仕入れ判定'!$A$6:$A$505,"<"&EDATE($A15,1),'仕入れ判定'!$AA$6:$AA$505,1),0)
A16: =EDATE(A15,1) | B16: =SUMIFS('仕入れ判定'!$Z$6:$Z$505,'仕入れ判定'!$A$6:$A$505,">="&$A16,'仕入れ判定'!$A$6:$A$505,"<"&EDATE($A16,1)) | C16: =SUMIFS('仕入れ判定'!$G$6:$G$505,'仕入れ判定'!$A$6:$A$505,">="&$A16,'仕入れ判定'!$A$6:$A$505,"<"&EDATE($A16,1),'仕入れ判定'!$Z$6:$Z$505,1) | D16: =SUMIFS('仕入れ判定'!$N$6:$N$505,'仕入れ判定'!$A$6:$A$505,">="&$A16,'仕入れ判定'!$A$6:$A$505,"<"&EDATE($A16,1),'仕入れ判定'!$Z$6:$Z$505,1) | E16: =SUMIFS('仕入れ判定'!$W$6:$W$505,'仕入れ判定'!$A$6:$A$505,">="&$A16,'仕入れ判定'!$A$6:$A$505,"<"&EDATE($A16,1),'仕入れ判定'!$AA$6:$AA$505,1) | F16: =SUMIFS('仕入れ判定'!$X$6:$X$505,'仕入れ判定'!$A$6:$A$505,">="&$A16,'仕入れ判定'!$A$6:$A$505,"<"&EDATE($A16,1),'仕入れ判定'!$AA$6:$AA$505,1) | G16: =IFERROR(E16/SUMIFS('仕入れ判定'!$G$6:$G$505,'仕入れ判定'!$A$6:$A$505,">="&$A16,'仕入れ判定'!$A$6:$A$505,"<"&EDATE($A16,1),'仕入れ判定'!$AA$6:$AA$505,1),0)
A17: =EDATE(A16,1) | B17: =SUMIFS('仕入れ判定'!$Z$6:$Z$505,'仕入れ判定'!$A$6:$A$505,">="&$A17,'仕入れ判定'!$A$6:$A$505,"<"&EDATE($A17,1)) | C17: =SUMIFS('仕入れ判定'!$G$6:$G$505,'仕入れ判定'!$A$6:$A$505,">="&$A17,'仕入れ判定'!$A$6:$A$505,"<"&EDATE($A17,1),'仕入れ判定'!$Z$6:$Z$505,1) | D17: =SUMIFS('仕入れ判定'!$N$6:$N$505,'仕入れ判定'!$A$6:$A$505,">="&$A17,'仕入れ判定'!$A$6:$A$505,"<"&EDATE($A17,1),'仕入れ判定'!$Z$6:$Z$505,1) | E17: =SUMIFS('仕入れ判定'!$W$6:$W$505,'仕入れ判定'!$A$6:$A$505,">="&$A17,'仕入れ判定'!$A$6:$A$505,"<"&EDATE($A17,1),'仕入れ判定'!$AA$6:$AA$505,1) | F17: =SUMIFS('仕入れ判定'!$X$6:$X$505,'仕入れ判定'!$A$6:$A$505,">="&$A17,'仕入れ判定'!$A$6:$A$505,"<"&EDATE($A17,1),'仕入れ判定'!$AA$6:$AA$505,1) | G17: =IFERROR(E17/SUMIFS('仕入れ判定'!$G$6:$G$505,'仕入れ判定'!$A$6:$A$505,">="&$A17,'仕入れ判定'!$A$6:$A$505,"<"&EDATE($A17,1),'仕入れ判定'!$AA$6:$AA$505,1),0)
A18: =EDATE(A17,1) | B18: =SUMIFS('仕入れ判定'!$Z$6:$Z$505,'仕入れ判定'!$A$6:$A$505,">="&$A18,'仕入れ判定'!$A$6:$A$505,"<"&EDATE($A18,1)) | C18: =SUMIFS('仕入れ判定'!$G$6:$G$505,'仕入れ判定'!$A$6:$A$505,">="&$A18,'仕入れ判定'!$A$6:$A$505,"<"&EDATE($A18,1),'仕入れ判定'!$Z$6:$Z$505,1) | D18: =SUMIFS('仕入れ判定'!$N$6:$N$505,'仕入れ判定'!$A$6:$A$505,">="&$A18,'仕入れ判定'!$A$6:$A$505,"<"&EDATE($A18,1),'仕入れ判定'!$Z$6:$Z$505,1) | E18: =SUMIFS('仕入れ判定'!$W$6:$W$505,'仕入れ判定'!$A$6:$A$505,">="&$A18,'仕入れ判定'!$A$6:$A$505,"<"&EDATE($A18,1),'仕入れ判定'!$AA$6:$AA$505,1) | F18: =SUMIFS('仕入れ判定'!$X$6:$X$505,'仕入れ判定'!$A$6:$A$505,">="&$A18,'仕入れ判定'!$A$6:$A$505,"<"&EDATE($A18,1),'仕入れ判定'!$AA$6:$AA$505,1) | G18: =IFERROR(E18/SUMIFS('仕入れ判定'!$G$6:$G$505,'仕入れ判定'!$A$6:$A$505,">="&$A18,'仕入れ判定'!$A$6:$A$505,"<"&EDATE($A18,1),'仕入れ判定'!$AA$6:$AA$505,1),0)
A19: =EDATE(A18,1) | B19: =SUMIFS('仕入れ判定'!$Z$6:$Z$505,'仕入れ判定'!$A$6:$A$505,">="&$A19,'仕入れ判定'!$A$6:$A$505,"<"&EDATE($A19,1)) | C19: =SUMIFS('仕入れ判定'!$G$6:$G$505,'仕入れ判定'!$A$6:$A$505,">="&$A19,'仕入れ判定'!$A$6:$A$505,"<"&EDATE($A19,1),'仕入れ判定'!$Z$6:$Z$505,1) | D19: =SUMIFS('仕入れ判定'!$N$6:$N$505,'仕入れ判定'!$A$6:$A$505,">="&$A19,'仕入れ判定'!$A$6:$A$505,"<"&EDATE($A19,1),'仕入れ判定'!$Z$6:$Z$505,1) | E19: =SUMIFS('仕入れ判定'!$W$6:$W$505,'仕入れ判定'!$A$6:$A$505,">="&$A19,'仕入れ判定'!$A$6:$A$505,"<"&EDATE($A19,1),'仕入れ判定'!$AA$6:$AA$505,1) | F19: =SUMIFS('仕入れ判定'!$X$6:$X$505,'仕入れ判定'!$A$6:$A$505,">="&$A19,'仕入れ判定'!$A$6:$A$505,"<"&EDATE($A19,1),'仕入れ判定'!$AA$6:$AA$505,1) | G19: =IFERROR(E19/SUMIFS('仕入れ判定'!$G$6:$G$505,'仕入れ判定'!$A$6:$A$505,">="&$A19,'仕入れ判定'!$A$6:$A$505,"<"&EDATE($A19,1),'仕入れ判定'!$AA$6:$AA$505,1),0)
A20: =EDATE(A19,1) | B20: =SUMIFS('仕入れ判定'!$Z$6:$Z$505,'仕入れ判定'!$A$6:$A$505,">="&$A20,'仕入れ判定'!$A$6:$A$505,"<"&EDATE($A20,1)) | C20: =SUMIFS('仕入れ判定'!$G$6:$G$505,'仕入れ判定'!$A$6:$A$505,">="&$A20,'仕入れ判定'!$A$6:$A$505,"<"&EDATE($A20,1),'仕入れ判定'!$Z$6:$Z$505,1) | D20: =SUMIFS('仕入れ判定'!$N$6:$N$505,'仕入れ判定'!$A$6:$A$505,">="&$A20,'仕入れ判定'!$A$6:$A$505,"<"&EDATE($A20,1),'仕入れ判定'!$Z$6:$Z$505,1) | E20: =SUMIFS('仕入れ判定'!$W$6:$W$505,'仕入れ判定'!$A$6:$A$505,">="&$A20,'仕入れ判定'!$A$6:$A$505,"<"&EDATE($A20,1),'仕入れ判定'!$AA$6:$AA$505,1) | F20: =SUMIFS('仕入れ判定'!$X$6:$X$505,'仕入れ判定'!$A$6:$A$505,">="&$A20,'仕入れ判定'!$A$6:$A$505,"<"&EDATE($A20,1),'仕入れ判定'!$AA$6:$AA$505,1) | G20: =IFERROR(E20/SUMIFS('仕入れ判定'!$G$6:$G$505,'仕入れ判定'!$A$6:$A$505,">="&$A20,'仕入れ判定'!$A$6:$A$505,"<"&EDATE($A20,1),'仕入れ判定'!$AA$6:$AA$505,1),0)
A21: =EDATE(A20,1) | B21: =SUMIFS('仕入れ判定'!$Z$6:$Z$505,'仕入れ判定'!$A$6:$A$505,">="&$A21,'仕入れ判定'!$A$6:$A$505,"<"&EDATE($A21,1)) | C21: =SUMIFS('仕入れ判定'!$G$6:$G$505,'仕入れ判定'!$A$6:$A$505,">="&$A21,'仕入れ判定'!$A$6:$A$505,"<"&EDATE($A21,1),'仕入れ判定'!$Z$6:$Z$505,1) | D21: =SUMIFS('仕入れ判定'!$N$6:$N$505,'仕入れ判定'!$A$6:$A$505,">="&$A21,'仕入れ判定'!$A$6:$A$505,"<"&EDATE($A21,1),'仕入れ判定'!$Z$6:$Z$505,1) | E21: =SUMIFS('仕入れ判定'!$W$6:$W$505,'仕入れ判定'!$A$6:$A$505,">="&$A21,'仕入れ判定'!$A$6:$A$505,"<"&EDATE($A21,1),'仕入れ判定'!$AA$6:$AA$505,1) | F21: =SUMIFS('仕入れ判定'!$X$6:$X$505,'仕入れ判定'!$A$6:$A$505,">="&$A21,'仕入れ判定'!$A$6:$A$505,"<"&EDATE($A21,1),'仕入れ判定'!$AA$6:$AA$505,1) | G21: =IFERROR(E21/SUMIFS('仕入れ判定'!$G$6:$G$505,'仕入れ判定'!$A$6:$A$505,">="&$A21,'仕入れ判定'!$A$6:$A$505,"<"&EDATE($A21,1),'仕入れ判定'!$AA$6:$AA$505,1),0)
A22: =EDATE(A21,1) | B22: =SUMIFS('仕入れ判定'!$Z$6:$Z$505,'仕入れ判定'!$A$6:$A$505,">="&$A22,'仕入れ判定'!$A$6:$A$505,"<"&EDATE($A22,1)) | C22: =SUMIFS('仕入れ判定'!$G$6:$G$505,'仕入れ判定'!$A$6:$A$505,">="&$A22,'仕入れ判定'!$A$6:$A$505,"<"&EDATE($A22,1),'仕入れ判定'!$Z$6:$Z$505,1) | D22: =SUMIFS('仕入れ判定'!$N$6:$N$505,'仕入れ判定'!$A$6:$A$505,">="&$A22,'仕入れ判定'!$A$6:$A$505,"<"&EDATE($A22,1),'仕入れ判定'!$Z$6:$Z$505,1) | E22: =SUMIFS('仕入れ判定'!$W$6:$W$505,'仕入れ判定'!$A$6:$A$505,">="&$A22,'仕入れ判定'!$A$6:$A$505,"<"&EDATE($A22,1),'仕入れ判定'!$AA$6:$AA$505,1) | F22: =SUMIFS('仕入れ判定'!$X$6:$X$505,'仕入れ判定'!$A$6:$A$505,">="&$A22,'仕入れ判定'!$A$6:$A$505,"<"&EDATE($A22,1),'仕入れ判定'!$AA$6:$AA$505,1) | G22: =IFERROR(E22/SUMIFS('仕入れ判定'!$G$6:$G$505,'仕入れ判定'!$A$6:$A$505,">="&$A22,'仕入れ判定'!$A$6:$A$505,"<"&EDATE($A22,1),'仕入れ判定'!$AA$6:$AA$505,1),0)
A24: 確定利益率＝確定利益 ÷ 確定買取額が入った商品の仕入れ額。見込み利益との差が、減額・送料の見込み違いの大きさ。
A26: 買取店別の減額（B列に買取店名を入れる。仕入れ判定シートの「買取店」と同じ表記で）
B27: 買取店 | C27: 査定済みの件数 | D27: 提示額の合計 | E27: 減額合計 | F27: 減額率
B28: 買取店X | C28: =IF($B28="","",SUMIFS('仕入れ判定'!$AA$6:$AA$505,'仕入れ判定'!$E$6:$E$505,$B28)) | D28: =IF($B28="","",SUMIFS('仕入れ判定'!$I$6:$I$505,'仕入れ判定'!$E$6:$E$505,$B28,'仕入れ判定'!$AA$6:$AA$505,1)) | E28: =IF($B28="","",SUMIFS('仕入れ判定'!$X$6:$X$505,'仕入れ判定'!$E$6:$E$505,$B28,'仕入れ判定'!$AA$6:$AA$505,1)) | F28: =IF(OR($B28="",N(D28)=0),"",E28/D28)
C29: =IF($B29="","",SUMIFS('仕入れ判定'!$AA$6:$AA$505,'仕入れ判定'!$E$6:$E$505,$B29)) | D29: =IF($B29="","",SUMIFS('仕入れ判定'!$I$6:$I$505,'仕入れ判定'!$E$6:$E$505,$B29,'仕入れ判定'!$AA$6:$AA$505,1)) | E29: =IF($B29="","",SUMIFS('仕入れ判定'!$X$6:$X$505,'仕入れ判定'!$E$6:$E$505,$B29,'仕入れ判定'!$AA$6:$AA$505,1)) | F29: =IF(OR($B29="",N(D29)=0),"",E29/D29)
C30: =IF($B30="","",SUMIFS('仕入れ判定'!$AA$6:$AA$505,'仕入れ判定'!$E$6:$E$505,$B30)) | D30: =IF($B30="","",SUMIFS('仕入れ判定'!$I$6:$I$505,'仕入れ判定'!$E$6:$E$505,$B30,'仕入れ判定'!$AA$6:$AA$505,1)) | E30: =IF($B30="","",SUMIFS('仕入れ判定'!$X$6:$X$505,'仕入れ判定'!$E$6:$E$505,$B30,'仕入れ判定'!$AA$6:$AA$505,1)) | F30: =IF(OR($B30="",N(D30)=0),"",E30/D30)
C31: =IF($B31="","",SUMIFS('仕入れ判定'!$AA$6:$AA$505,'仕入れ判定'!$E$6:$E$505,$B31)) | D31: =IF($B31="","",SUMIFS('仕入れ判定'!$I$6:$I$505,'仕入れ判定'!$E$6:$E$505,$B31,'仕入れ判定'!$AA$6:$AA$505,1)) | E31: =IF($B31="","",SUMIFS('仕入れ判定'!$X$6:$X$505,'仕入れ判定'!$E$6:$E$505,$B31,'仕入れ判定'!$AA$6:$AA$505,1)) | F31: =IF(OR($B31="",N(D31)=0),"",E31/D31)
C32: =IF($B32="","",SUMIFS('仕入れ判定'!$AA$6:$AA$505,'仕入れ判定'!$E$6:$E$505,$B32)) | D32: =IF($B32="","",SUMIFS('仕入れ判定'!$I$6:$I$505,'仕入れ判定'!$E$6:$E$505,$B32,'仕入れ判定'!$AA$6:$AA$505,1)) | E32: =IF($B32="","",SUMIFS('仕入れ判定'!$X$6:$X$505,'仕入れ判定'!$E$6:$E$505,$B32,'仕入れ判定'!$AA$6:$AA$505,1)) | F32: =IF(OR($B32="",N(D32)=0),"",E32/D32)
C33: =IF($B33="","",SUMIFS('仕入れ判定'!$AA$6:$AA$505,'仕入れ判定'!$E$6:$E$505,$B33)) | D33: =IF($B33="","",SUMIFS('仕入れ判定'!$I$6:$I$505,'仕入れ判定'!$E$6:$E$505,$B33,'仕入れ判定'!$AA$6:$AA$505,1)) | E33: =IF($B33="","",SUMIFS('仕入れ判定'!$X$6:$X$505,'仕入れ判定'!$E$6:$E$505,$B33,'仕入れ判定'!$AA$6:$AA$505,1)) | F33: =IF(OR($B33="",N(D33)=0),"",E33/D33)
C34: =IF($B34="","",SUMIFS('仕入れ判定'!$AA$6:$AA$505,'仕入れ判定'!$E$6:$E$505,$B34)) | D34: =IF($B34="","",SUMIFS('仕入れ判定'!$I$6:$I$505,'仕入れ判定'!$E$6:$E$505,$B34,'仕入れ判定'!$AA$6:$AA$505,1)) | E34: =IF($B34="","",SUMIFS('仕入れ判定'!$X$6:$X$505,'仕入れ判定'!$E$6:$E$505,$B34,'仕入れ判定'!$AA$6:$AA$505,1)) | F34: =IF(OR($B34="",N(D34)=0),"",E34/D34)
C35: =IF($B35="","",SUMIFS('仕入れ判定'!$AA$6:$AA$505,'仕入れ判定'!$E$6:$E$505,$B35)) | D35: =IF($B35="","",SUMIFS('仕入れ判定'!$I$6:$I$505,'仕入れ判定'!$E$6:$E$505,$B35,'仕入れ判定'!$AA$6:$AA$505,1)) | E35: =IF($B35="","",SUMIFS('仕入れ判定'!$X$6:$X$505,'仕入れ判定'!$E$6:$E$505,$B35,'仕入れ判定'!$AA$6:$AA$505,1)) | F35: =IF(OR($B35="",N(D35)=0),"",E35/D35)
A37: 減額率が高い買取店は、梱包の見直しか、送り先の変更を検討する。
