Workbook

Sheet 使い方
A1: Amazon物販 利益・現金・在庫の監査キット
A3: 入力するのは黄色のセル（青い文字）だけです。ほかは自動で計算されます。【見本】の6か月分は架空の数字です。使うときは上書きしてください。
A5: 1. 月次シート：1か月1行。数字はセラーセントラルの「ペイメント」→「日付範囲別レポート」と、自分の仕入れの記録から入れる
A6: ・販売手数料・FBA配送手数料・保管手数料・返金額：日付範囲別レポートの各合計（マイナス表示ならプラスに直して入れる）
A7: ・1個あたり着地原価：工場への支払い＋国際送料＋関税＋通関・検品・国内配送 を、その仕入れの個数で割った額
A8: ・返品個数のうち、売り物にならなかった個数を「再販不可」に入れる（再販できた分は在庫に戻るので原価から外れる）
A9: ・広告費は、Amazonの入金から引かれていても、カードで払っていても、ここに入れる
A10: ・Amazon以外の支払い：カードで払った広告費・倉庫への送料など、入金から引かれていない支払い（現金の増減の計算に使う）
A11: 2. 判定：赤字＝利益がマイナス／注意＝広告前利益率・返品率・在庫月数のどれかが設定の基準を外れている
A12: 3. 内訳シート：期間全体で、売上がどこに消えたかを、大きい順に並べる
A13: 4. 改善シミュレーション：原価・価格・広告・返品・FBA手数料を変えると、1個あたりの利益がどう変わるかを見る
A15: 見る順番
... A18: 注意：この表の利益は、事務所・ツール代などの固定費と税金を引く前の数字です。消費税の扱いは、自分の申告方法に合わせて読み替えてください。

Sheet 設定
A1: 判定の基準（初期値。自分の商品に合わせて変える）
B4: 広告前利益率の下限 | C4: 0.1 | D4: これより薄いと、広告と返品で赤字になりやすい
B5: 返品率の上限 | C5: 0.05 | D5: これを超えたら、不良・説明文・梱包を点検する
B6: 在庫月数の上限 | C6: 3 | D6: 今の販売ペースで何か月分の在庫か。超えると保管料と資金が寝る

Sheet 月次
A1: 月次の監査
A2: 緑の見出し＝入力／灰色の見出し＝自動計算。1か月1行。【見本】の6か月分は架空の数字です。
A3: 実質売上＝売上−返金額／原価＝（販売個数−再販できた返品）×着地原価／利益＝実質売上−原価−Amazon費用−広告費
A5: 月 | B5: 売上 （税込） | C5: 販売個数 | D5: 販売 手数料 | E5: FBA配送 手数料 | F5: 在庫 保管手数料 | G5: その他の Amazon費用 | H5: 広告費 | I5: 返金額 | J5: 返品 個数 | K5: うち 再販不可 | L5: 1個あたり 着地原価 | M5: 月末の 在庫個数 | N5: 仕入れの 支払額 | O5: Amazonから の入金額 | P5: Amazon以外 の支払い | Q5: 実質売上 | R5: 原価 | S5: Amazon 費用合計 | T5: 広告前 利益 | U5: 利益 | V5: 1個あたり 利益 | W5: 広告前 利益率 | X5: 原価率 | Y5: Amazon 費用率 | Z5: 広告 比率 | AA5: 返品率 | AB5: 在庫 月数 | AC5: 現金の 増減 | AD5: 判定
A6: 46113 | B6: 1380000 | C6: 100 | D6: 207000 | E6: 132000 | F6: 9000 | G6: 4000 | H6: 52000 | I6: 41400 | J6: 3 | K6: 1 | L6: 8200 | M6: 420 | N6: 0 | O6: 980000 | P6: 52000 | Q6: =IF($B6="","",$B6-$I6) | R6: =IF($B6="","",($C6-($J6-$K6))*$L6) | S6: =IF($B6="","",$D6+$E6+$F6+$G6) | T6: =IF($B6="","",$Q6-$R6-$S6) | U6: =IF($B6="","",$T6-$H6) | V6: =IF($B6="","",IF($C6-$J6>0,$U6/($C6-$J6),"")) | W6: =IF(N($Q6)=0,"",$T6/$Q6) | X6: =IF(N($Q6)=0,"",$R6/$Q6) | Y6: =IF(N($B6)=0,"",$S6/$B6) | Z6: =IF(N($B6)=0,"",$H6/$B6) | AA6: =IF(N($C6)=0,"",$J6/$C6) | AB6: =IF($B6="","",IF($C6-$J6>0,$M6/($C6-$J6),"")) | AC6: =IF($B6="","",$O6-$N6-$P6) | AD6: =IF($B6="","",IF(N($U6)<0,"赤字",IF(OR(N($W6)<'設定'!$C$4,N($AA6)>'設定'!$C$5,N($AB6)>'設定'!$C$6),"注意","OK")))
A7: 46143 | B7: 1518000 | C7: 110 | D7: 227700 | E7: 145200 | F7: 10000 | G7: 4000 | H7: 60000 | I7: 55200 | J7: 4 | K7: 2 | L7: 8200 | M7: 310 | N7: 0 | O7: 1090000 | P7: 60000 | Q7: =IF($B7="","",$B7-$I7) | R7: =IF($B7="","",($C7-($J7-$K7))*$L7) | S7: =IF($B7="","",$D7+$E7+$F7+$G7) | T7: =IF($B7="","",$Q7-$R7-$S7) | U7: =IF($B7="","",$T7-$H7) | V7: =IF($B7="","",IF($C7-$J7>0,$U7/($C7-$J7),"")) | W7: =IF(N($Q7)=0,"",$T7/$Q7) | X7: =IF(N($Q7)=0,"",$R7/$Q7) | Y7: =IF(N($B7)=0,"",$S7/$B7) | Z7: =IF(N($B7)=0,"",$H7/$B7) | AA7: =IF(N($C7)=0,"",$J7/$C7) | AB7: =IF($B7="","",IF($C7-$J7>0,$M7/($C7-$J7),"")) | AC7: =IF($B7="","",$O7-$N7-$P7) | AD7: =IF($B7="","",IF(N($U7)<0,"赤字",IF(OR(N($W7)<'設定'!$C$4,N($AA7)>'設定'!$C$5,N($AB7)>'設定'!$C$6),"注意","OK")))
A8: 46174 | B8: 1656000 | C8: 120 | D8: 248400 | E8: 158400 | F8: 9500 | G8: 4000 | H8: 66000 | I8: 41400 | J8: 3 | K8: 1 | L8: 8200 | M8: 190 | N8: 2460000 | O8: 1190000 | P8: 66000 | Q8: =IF($B8="","",$B8-$I8) | R8: =IF($B8="","",($C8-($J8-$K8))*$L8) | S8: =IF($B8="","",$D8+$E8+$F8+$G8) | T8: =IF($B8="","",$Q8-$R8-$S8) | U8: =IF($B8="","",$T8-$H8) | V8: =IF($B8="","",IF($C8-$J8>0,$U8/($C8-$J8),"")) | W8: =IF(N($Q8)=0,"",$T8/$Q8) | X8: =IF(N($Q8)=0,"",$R8/$Q8) | Y8: =IF(N($B8)=0,"",$S8/$B8) | Z8: =IF(N($B8)=0,"",$H8/$B8) | AA8: =IF(N($C8)=0,"",$J8/$C8) | AB8: =IF($B8="","",IF($C8-$J8>0,$M8/($C8-$J8),"")) | AC8: =IF($B8="","",$O8-$N8-$P8) | AD8: =IF($B8="","",IF(N($U8)<0,"赤字",IF(OR(N($W8)<'設定'!$C$4,N($AA8)>'設定'!$C$5,N($AB8)>'設定'!$C$6),"注意","OK")))
A9: 46204 | B9: 1794000 | C9: 130 | D9: 269100 | E9: 171600 | F9: 12000 | G9: 4000 | H9: 78000 | I9: 69000 | J9: 5 | K9: 3 | L9: 8400 | M9: 560 | N9: 0 | O9: 1260000 | P9: 78000 | Q9: =IF($B9="","",$B9-$I9) | R9: =IF($B9="","",($C9-($J9-$K9))*$L9) | S9: =IF($B9="","",$D9+$E9+$F9+$G9) | T9: =IF($B9="","",$Q9-$R9-$S9) | U9: =IF($B9="","",$T9-$H9) | V9: =IF($B9="","",IF($C9-$J9>0,$U9/($C9-$J9),"")) | W9: =IF(N($Q9)=0,"",$T9/$Q9) | X9: =IF(N($Q9)=0,"",$R9/$Q9) | Y9: =IF(N($B9)=0,"",$S9/$B9) | Z9: =IF(N($B9)=0,"",$H9/$B9) | AA9: =IF(N($C9)=0,"",$J9/$C9) | AB9: =IF($B9="","",IF($C9-$J9>0,$M9/($C9-$J9),"")) | AC9: =IF($B9="","",$O9-$N9-$P9) | AD9: =IF($B9="","",IF(N($U9)<0,"赤字",IF(OR(N($W9)<'設定'!$C$4,N($AA9)>'設定'!$C$5,N($AB9)>'設定'!$C$6),"注意","OK")))
A10: 46235 | B10: 1656000 | C10: 120 | D10: 248400 | E10: 158400 | F10: 15000 | G10: 4000 | H10: 84000 | I10: 82800 | J10: 6 | K10: 3 | L10: 8400 | M10: 440 | N10: 0 | O10: 1170000 | P10: 84000 | Q10: =IF($B10="","",$B10-$I10) | R10: =IF($B10="","",($C10-($J10-$K10))*$L10) | S10: =IF($B10="","",$D10+$E10+$F10+$G10) | T10: =IF($B10="","",$Q10-$R10-$S10) | U10: =IF($B10="","",$T10-$H10) | V10: =IF($B10="","",IF($C10-$J10>0,$U10/($C10-$J10),"")) | W10: =IF(N($Q10)=0,"",$T10/$Q10) | X10: =IF(N($Q10)=0,"",$R10/$Q10) | Y10: =IF(N($B10)=0,"",$S10/$B10) | Z10: =IF(N($B10)=0,"",$H10/$B10) | AA10: =IF(N($C10)=0,"",$J10/$C10) | AB10: =IF($B10="","",IF($C10-$J10>0,$M10/($C10-$J10),"")) | AC10: =IF($B10="","",$O10-$N10-$P10) | AD10: =IF($B10="","",IF(N($U10)<0,"赤字",IF(OR(N($W10)<'設定'!$C$4,N($AA10)>'設定'!$C$5,N($AB10)>'設定'!$C$6),"注意","OK")))
A11: 46266 | B11: 1380000 | C11: 100 | D11: 207000 | E11: 132000 | F11: 18000 | G11: 4000 | H11: 90000 | I11: 55200 | J11: 4 | K11: 2 | L11: 8400 | M11: 900 | N11: 4200000 | O11: 990000 | P11: 90000 | Q11: =IF($B11="","",$B11-$I11) | R11: =IF($B11="","",($C11-($J11-$K11))*$L11) | S11: =IF($B11="","",$D11+$E11+$F11+$G11) | T11: =IF($B11="","",$Q11-$R11-$S11) | U11: =IF($B11="","",$T11-$H11) | V11: =IF($B11="","",IF($C11-$J11>0,$U11/($C11-$J11),"")) | W11: =IF(N($Q11)=0,"",$T11/$Q11) | X11: =IF(N($Q11)=0,"",$R11/$Q11) | Y11: =IF(N($B11)=0,"",$S11/$B11) | Z11: =IF(N($B11)=0,"",$H11/$B11) | AA11: =IF(N($C11)=0,"",$J11/$C11) | AB11: =IF($B11="","",IF($C11-$J11>0,$M11/($C11-$J11),"")) | AC11: =IF($B11="","",$O11-$N11-$P11) | AD11: =IF($B11="","",IF(N($U11)<0,"赤字",IF(OR(N($W11)<'設定'!$C$4,N($AA11)>'設定'!$C$5,N($AB11)>'設定'!$C$6),"注意","OK")))
Q12: =IF($B12="","",$B12-$I12) | R12: =IF($B12="","",($C12-($J12-$K12))*$L12) | S12: =IF($B12="","",$D12+$E12+$F12+$G12) | T12: =IF($B12="","",$Q12-$R12-$S12) | U12: =IF($B12="","",$T12-$H12) | V12: =IF($B12="","",IF($C12-$J12>0,$U12/($C12-$J12),"")) | W12: =IF(N($Q12)=0,"",$T12/$Q12) | X12: =IF(N($Q12)=0,"",$R12/$Q12) | Y12: =IF(N($B12)=0,"",$S12/$B12) | Z12: =IF(N($B12)=0,"",$H12/$B12) | AA12: =IF(N($C12)=0,"",$J12/$C12) | AB12: =IF($B12="","",IF($C12-$J12>0,$M12/($C12-$J12),"")) | AC12: =IF($B12="","",$O12-$N12-$P12) | AD12: =IF($B12="","",IF(N($U12)<0,"赤字",IF(OR(N($W12)<'設定'!$C$4,N($AA12)>'設定'!$C$5,N($AB12)>'設定'!$C$6),"注意","OK")))
Q13: =IF($B13="","",$B13-$I13) | R13: =IF($B13="","",($C13-($J13-$K13))*$L13) | S13: =IF($B13="","",$D13+$E13+$F13+$G13) | T13: =IF($B13="","",$Q13-$R13-$S13) | U13: =IF($B13="","",$T13-$H13) | V13: =IF($B13="","",IF($C13-$J13>0,$U13/($C13-$J13),"")) | W13: =IF(N($Q13)=0,"",$T13/$Q13) | X13: =IF(N($Q13)=0,"",$R13/$Q13) | Y13: =IF(N($B13)=0,"",$S13/$B13) | Z13: =IF(N($B13)=0,"",$H13/$B13) | AA13: =IF(N($C13)=0,"",$J13/$C13) | AB13: =IF($B13="","",IF($C13-$J13>0,$M13/($C13-$J13),"")) | AC13: =IF($B13="","",$O13-$N13-$P13) | AD13: =IF($B13="","",IF(N($U13)<0,"赤字",IF(OR(N($W13)<'設定'!$C$4,N($AA13)>'設定'!$C$5,N($AB13)>'設定'!$C$6),"注意","OK")))
Q14: =IF($B14="","",$B14-$I14) | R14: =IF($B14="","",($C14-($J14-$K14))*$L14) | S14: =IF($B14="","",$D14+$E14+$F14+$G14) | T14: =IF($B14="","",$Q14-$R14-$S14) | U14: =IF($B14="","",$T14-$H14) | V14: =IF($B14="","",IF($C14-$J14>0,$U14/($C14-$J14),"")) | W14: =IF(N($Q14)=0,"",$T14/$Q14) | X14: =IF(N($Q14)=0,"",$R14/$Q14) | Y14: =IF(N($B14)=0,"",$S14/$B14) | Z14: =IF(N($B14)=0,"",$H14/$B14) | AA14: =IF(N($C14)=0,"",$J14/$C14) | AB14: =IF($B14="","",IF($C14-$J14>0,$M14/($C14-$J14),"")) | AC14: =IF($B14="","",$O14-$N14-$P14) | AD14: =IF($B14="","",IF(N($U14)<0,"赤字",IF(OR(N($W14)<'設定'!$C$4,N($AA14)>'設定'!$C$5,N($AB14)>'設定'!$C$6),"注意","OK")))
Q15: =IF($B15="","",$B15-$I15) | R15: =IF($B15="","",($C15-($J15-$K15))*$L15) | S15: =IF($B15="","",$D15+$E15+$F15+$G15) | T15: =IF($B15="","",$Q15-$R15-$S15) | U15: =IF($B15="","",$T15-$H15) | V15: =IF($B15="","",IF($C15-$J15>0,$U15/($C15-$J15),"")) | W15: =IF(N($Q15)=0,"",$T15/$Q15) | X15: =IF(N($Q15)=0,"",$R15/$Q15) | Y15: =IF(N($B15)=0,"",$S15/$B15) | Z15: =IF(N($B15)=0,"",$H15/$B15) | AA15: =IF(N($C15)=0,"",$J15/$C15) | AB15: =IF($B15="","",IF($C15-$J15>0,$M15/($C15-$J15),"")) | AC15: =IF($B15="","",$O15-$N15-$P15) | AD15: =IF($B15="","",IF(N($U15)<0,"赤字",IF(OR(N($W15)<'設定'!$C$4,N($AA15)>'設定'!$C$5,N($AB15)>'設定'!$C$6),"注意","OK")))
Q16: =IF($B16="","",$B16-$I16) | R16: =IF($B16="","",($C16-($J16-$K16))*$L16) | S16: =IF($B16="","",$D16+$E16+$F16+$G16) | T16: =IF($B16="","",$Q16-$R16-$S16) | U16: =IF($B16="","",$T16-$H16) | V16: =IF($B16="","",IF($C16-$J16>0,$U16/($C16-$J16),"")) | W16: =IF(N($Q16)=0,"",$T16/$Q16) | X16: =IF(N($Q16)=0,"",$R16/$Q16) | Y16: =IF(N($B16)=0,"",$S16/$B16) | Z16: =IF(N($B16)=0,"",$H16/$B16) | AA16: =IF(N($C16)=0,"",$J16/$C16) | AB16: =IF($B16="","",IF($C16-$J16>0,$M16/($C16-$J16),"")) | AC16: =IF($B16="","",$O16-$N16-$P16) | AD16: =IF($B16="","",IF(N($U16)<0,"赤字",IF(OR(N($W16)<'設定'!$C$4,N($AA16)>'設定'!$C$5,N($AB16)>'設定'!$C$6),"注意","OK")))
Q17: =IF($B17="","",$B17-$I17) | R17: =IF($B17="","",($C17-($J17-$K17))*$L17) | S17: =IF($B17="","",$D17+$E17+$F17+$G17) | T17: =IF($B17="","",$Q17-$R17-$S17) | U17: =IF($B17="","",$T17-$H17) | V17: =IF($B17="","",IF($C17-$J17>0,$U17/($C17-$J17),"")) | W17: =IF(N($Q17)=0,"",$T17/$Q17) | X17: =IF(N($Q17)=0,"",$R17/$Q17) | Y17: =IF(N($B17)=0,"",$S17/$B17) | Z17: =IF(N($B17)=0,"",$H17/$B17) | AA17: =IF(N($C17)=0,"",$J17/$C17) | AB17: =IF($B17="","",IF($C17-$J17>0,$M17/($C17-$J17),"")) | AC17: =IF($B17="","",$O17-$N17-$P17) | AD17: =IF($B17="","",IF(N($U17)<0,"赤字",IF(OR(N($W17)<'設定'!$C$4,N($AA17)>'設定'!$C$5,N($AB17)>'設定'!$C$6),"注意","OK")))
Q18: =IF($B18="","",$B18-$I18) | R18: =IF($B18="","",($C18-($J18-$K18))*$L18) | S18: =IF($B18="","",$D18+$E18+$F18+$G18) | T18: =IF($B18="","",$Q18-$R18-$S18) | U18: =IF($B18="","",$T18-$H18) | V18: =IF($B18="","",IF($C18-$J18>0,$U18/($C18-$J18),"")) | W18: =IF(N($Q18)=0,"",$T18/$Q18) | X18: =IF(N($Q18)=0,"",$R18/$Q18) | Y18: =IF(N($B18)=0,"",$S18/$B18) | Z18: =IF(N($B18)=0,"",$H18/$B18) | AA18: =IF(N($C18)=0,"",$J18/$C18) | AB18: =IF($B18="","",IF($C18-$J18>0,$M18/($C18-$J18),"")) | AC18: =IF($B18="","",$O18-$N18-$P18) | AD18: =IF($B18="","",IF(N($U18)<0,"赤字",IF(OR(N($W18)<'設定'!$C$4,N($AA18)>'設定'!$C$5,N($AB18)>'設定'!$C$6),"注意","OK")))
Q19: =IF($B19="","",$B19-$I19) | R19: =IF($B19="","",($C19-($J19-$K19))*$L19) | S19: =IF($B19="","",$D19+$E19+$F19+$G19) | T19: =IF($B19="","",$Q19-$R19-$S19) | U19: =IF($B19="","",$T19-$H19) | V19: =IF($B19="","",IF($C19-$J19>0,$U19/($C19-$J19),"")) | W19: =IF(N($Q19)=0,"",$T19/$Q19) | X19: =IF(N($Q19)=0,"",$R19/$Q19) | Y19: =IF(N($B19)=0,"",$S19/$B19) | Z19: =IF(N($B19)=0,"",$H19/$B19) | AA19: =IF(N($C19)=0,"",$J19/$C19) | AB19: =IF($B19="","",IF($C19-$J19>0,$M19/($C19-$J19),"")) | AC19: =IF($B19="","",$O19-$N19-$P19) | AD19: =IF($B19="","",IF(N($U19)<0,"赤字",IF(OR(N($W19)<'設定'!$C$4,N($AA19)>'設定'!$C$5,N($AB19)>'設定'!$C$6),"注意","OK")))
Q20: =IF($B20="","",$B20-$I20) | R20: =IF($B20="","",($C20-($J20-$K20))*$L20) | S20: =IF($B20="","",$D20+$E20+$F20+$G20) | T20: =IF($B20="","",$Q20-$R20-$S20) | U20: =IF($B20="","",$T20-$H20) | V20: =IF($B20="","",IF($C20-$J20>0,$U20/($C20-$J20),"")) | W20: =IF(N($Q20)=0,"",$T20/$Q20) | X20: =IF(N($Q20)=0,"",$R20/$Q20) | Y20: =IF(N($B20)=0,"",$S20/$B20) | Z20: =IF(N($B20)=0,"",$H20/$B20) | AA20: =IF(N($C20)=0,"",$J20/$C20) | AB20: =IF($B20="","",IF($C20-$J20>0,$M20/($C20-$J20),"")) | AC20: =IF($B20="","",$O20-$N20-$P20) | AD20: =IF($B20="","",IF(N($U20)<0,"赤字",IF(OR(N($W20)<'設定'!$C$4,N($AA20)>'設定'!$C$5,N($AB20)>'設定'!$C$6),"注意","OK")))
Q21: =IF($B21="","",$B21-$I21) | R21: =IF($B21="","",($C21-($J21-$K21))*$L21) | S21: =IF($B21="","",$D21+$E21+$F21+$G21) | T21: =IF($B21="","",$Q21-$R21-$S21) | U21: =IF($B21="","",$T21-$H21) | V21: =IF($B21="","",IF($C21-$J21>0,$U21/($C21-$J21),"")) | W21: =IF(N($Q21)=0,"",$T21/$Q21) | X21: =IF(N($Q21)=0,"",$R21/$Q21) | Y21: =IF(N($B21)=0,"",$S21/$B21) | Z21: =IF(N($B21)=0,"",$H21/$B21) | AA21: =IF(N($C21)=0,"",$J21/$C21) | AB21: =IF($B21="","",IF($C21-$J21>0,$M21/($C21-$J21),"")) | AC21: =IF($B21="","",$O21-$N21-$P21) | AD21: =IF($B21="","",IF(N($U21)<0,"赤字",IF(OR(N($W21)<'設定'!$C$4,N($AA21)>'設定'!$C$5,N($AB21)>'設定'!$C$6),"注意","OK")))
Q22: =IF($B22="","",$B22-$I22) | R22: =IF($B22="","",($C22-($J22-$K22))*$L22) | S22: =IF($B22="","",$D22+$E22+$F22+$G22) | T22: =IF($B22="","",$Q22-$R22-$S22) | U22: =IF($B22="","",$T22-$H22) | V22: =IF($B22="","",IF($C22-$J22>0,$U22/($C22-$J22),"")) | W22: =IF(N($Q22)=0,"",$T22/$Q22) | X22: =IF(N($Q22)=0,"",$R22/$Q22) | Y22: =IF(N($B22)=0,"",$S22/$B22) | Z22: =IF(N($B22)=0,"",$H22/$B22) | AA22: =IF(N($C22)=0,"",$J22/$C22) | AB22: =IF($B22="","",IF($C22-$J22>0,$M22/($C22-$J22),"")) | AC22: =IF($B22="","",$O22-$N22-$P22) | AD22: =IF($B22="","",IF(N($U22)<0,"赤字",IF(OR(N($W22)<'設定'!$C$4,N($AA22)>'設定'!$C$5,N($AB22)>'設定'!$C$6),"注意","OK")))
Q23: =IF($B23="","",$B23-$I23) | R23: =IF($B23="","",($C23-($J23-$K23))*$L23) | S23: =IF($B23="","",$D23+$E23+$F23+$G23) | T23: =IF($B23="","",$Q23-$R23-$S23) | U23: =IF($B23="","",$T23-$H23) | V23: =IF($B23="","",IF($C23-$J23>0,$U23/($C23-$J23),"")) | W23: =IF(N($Q23)=0,"",$T23/$Q23) | X23: =IF(N($Q23)=0,"",$R23/$Q23) | Y23: =IF(N($B23)=0,"",$S23/$B23) | Z23: =IF(N($B23)=0,"",$H23/$B23) | AA23: =IF(N($C23)=0,"",$J23/$C23) | AB23: =IF($B23="","",IF($C23-$J23>0,$M23/($C23-$J23),"")) | AC23: =IF($B23="","",$O23-$N23-$P23) | AD23: =IF($B23="","",IF(N($U23)<0,"赤字",IF(OR(N($W23)<'設定'!$C$4,N($AA23)>'設定'!$C$5,N($AB23)>'設定'!$C$6),"注意","OK")))
... Q29: =IF($B29="","",$B29-$I29) | R29: =IF($B29="","",($C29-($J29-$K29))*$L29) | S29: =IF($B29="","",$D29+$E29+$F29+$G29) | T29: =IF($B29="","",$Q29-$R29-$S29) | U29: =IF($B29="","",$T29-$H29) | V29: =IF($B29="","",IF($C29-$J29>0,$U29/($C29-$J29),"")) | W29: =IF(N($Q29)=0,"",$T29/$Q29) | X29: =IF(N($Q29)=0,"",$R29/$Q29) | Y29: =IF(N($B29)=0,"",$S29/$B29) | Z29: =IF(N($B29)=0,"",$H29/$B29) | AA29: =IF(N($C29)=0,"",$J29/$C29) | AB29: =IF($B29="","",IF($C29-$J29>0,$M29/($C29-$J29),"")) | AC29: =IF($B29="","",$O29-$N29-$P29) | AD29: =IF($B29="","",IF(N($U29)<0,"赤字",IF(OR(N($W29)<'設定'!$C$4,N($AA29)>'設定'!$C$5,N($AB29)>'設定'!$C$6),"注意","OK")))

Sheet 内訳
A1: 売上はどこに消えたか（月次シートの全期間）
A3: 期間の合計
B4: 売上（税込） | C4: =SUM('月次'!$B$6:$B$29)
B5: 販売個数 | C5: =SUM('月次'!$C$6:$C$29)
B6: 返品個数 | C6: =SUM('月次'!$J$6:$J$29)
B7: 実質の販売個数 | C7: =C5-C6
B8: 利益 | C8: =SUM('月次'!$U$6:$U$29)
B9: 1個あたり利益 | C9: =IF(C7>0,C8/C7,0)
B10: 広告前利益 | C10: =SUM('月次'!$T$6:$T$29)
B11: 広告前利益率 | C11: =IFERROR(C10/SUM('月次'!$Q$6:$Q$29),0)
B12: 現金の増減 | C12: =SUM('月次'!$AC$6:$AC$29)
A15: 売上から出ていったお金（売上に対する割合）
B16: 項目 | C16: 金額 | D16: 売上比 | E16: 1個あたり | F16: 順位
B17: 商品原価 | C17: =SUM('月次'!$R$6:$R$29) | D17: =IF($C$4>0,C17/$C$4,0) | E17: =IF($C$7>0,C17/$C$7,0) | F17: =RANK(C17,$C$17:$C$23)
B18: 販売手数料 | C18: =SUM('月次'!$D$6:$D$29) | D18: =IF($C$4>0,C18/$C$4,0) | E18: =IF($C$7>0,C18/$C$7,0) | F18: =RANK(C18,$C$17:$C$23)
B19: FBA配送手数料 | C19: =SUM('月次'!$E$6:$E$29) | D19: =IF($C$4>0,C19/$C$4,0) | E19: =IF($C$7>0,C19/$C$7,0) | F19: =RANK(C19,$C$17:$C$23)
B20: 在庫保管手数料 | C20: =SUM('月次'!$F$6:$F$29) | D20: =IF($C$4>0,C20/$C$4,0) | E20: =IF($C$7>0,C20/$C$7,0) | F20: =RANK(C20,$C$17:$C$23)
B21: その他のAmazon費用 | C21: =SUM('月次'!$G$6:$G$29) | D21: =IF($C$4>0,C21/$C$4,0) | E21: =IF($C$7>0,C21/$C$7,0) | F21: =RANK(C21,$C$17:$C$23)
B22: 広告費 | C22: =SUM('月次'!$H$6:$H$29) | D22: =IF($C$4>0,C22/$C$4,0) | E22: =IF($C$7>0,C22/$C$7,0) | F22: =RANK(C22,$C$17:$C$23)
B23: 返金 | C23: =SUM('月次'!$I$6:$I$29) | D23: =IF($C$4>0,C23/$C$4,0) | E23: =IF($C$7>0,C23/$C$7,0) | F23: =RANK(C23,$C$17:$C$23)
B24: 残った利益 | C24: =C8 | D24: =IF($C$4>0,C8/$C$4,0) | E24: =C9
B26: 順位1〜2の項目から手を付ける。広告は最後（広告前の利益が薄いまま広告を止めても、売上が落ちるだけで赤字は残りやすい）

Sheet 改善シミュレーション
A1: 改善シミュレーション（1個あたり。内訳シートの期間平均が基準）
A2: 販売個数は変わらないものとして計算します。値上げで販売個数が減る影響は入っていません。
B4: 変える条件
B5: 販売価格 | C5: 0 | D5: ＋なら値上げ。販売手数料・返金も同じ割合で変わる
B6: 着地原価 | C6: -0.05 | D6: 工場との交渉・発注ロット・輸送の見直し
B7: 広告費 | C7: 0 | D7: −なら削減
B8: 返品・返金 | C8: -0.3 | D8: 不良・説明文・梱包の改善
B9: FBA配送手数料 | C9: 0 | D9: 梱包を小さくしてサイズ区分を下げるなど
B11: 項目（1個あたり） | C11: いま | D11: 変えた後 | E11: 差
B12: 売上 | C12: =IF('内訳'!$C$7>0,SUM('月次'!$B$6:$B$29)/'内訳'!$C$7,0) | D12: =C12*(1+$C$5) | E12: =D12-C12
B13: 返金 | C13: =IF('内訳'!$C$7>0,'内訳'!$C$23/'内訳'!$C$7,0) | D13: =C13*(1+$C$5)*(1+$C$8) | E13: =D13-C13
B14: 商品原価 | C14: =IF('内訳'!$C$7>0,'内訳'!$C$17/'内訳'!$C$7,0) | D14: =C14*(1+$C$6) | E14: =D14-C14
B15: 販売手数料 | C15: =IF('内訳'!$C$7>0,'内訳'!$C$18/'内訳'!$C$7,0) | D15: =C15*(1+$C$5) | E15: =D15-C15
B16: FBA配送手数料 | C16: =IF('内訳'!$C$7>0,'内訳'!$C$19/'内訳'!$C$7,0) | D16: =C16*(1+$C$9) | E16: =D16-C16
B17: 保管・その他のAmazon費用 | C17: =IF('内訳'!$C$7>0,'内訳'!$C$20/'内訳'!$C$7,0)+IF('内訳'!$C$7>0,'内訳'!$C$21/'内訳'!$C$7,0) | D17: =C17 | E17: =D17-C17
B18: 広告費 | C18: =IF('内訳'!$C$7>0,'内訳'!$C$22/'内訳'!$C$7,0) | D18: =C18*(1+$C$7) | E18: =D18-C18
B19: 1個あたり利益 | C19: =C12-SUM(C13:C18) | D19: =D12-SUM(D13:D18) | E19: =D19-C19
B20: 期間の利益（実質の販売個数×1個あたり） | C20: =C19*'内訳'!$C$7 | D20: =D19*'内訳'!$C$7
